Workbook

Sheet Target List
A1: Stimblue+ Strategic Target List
A2: March 2026 | Revenue model: Hectares × 80% Coverage × 2 L/app × 3 Applications/yr × €7.50/L
A4: Company | B4: HQ Country | C4: Business Type | D4: Main Focus Crops | E4: Food Company Matrix Score | F4: Tier | G4: Year 4 Revenue (€, projected) | H4: Hectares Controlled | I4: Notes / Evidence
A5: L5 — Under Contract | G5: Year 4 includes a Year 1 low/no rev trial year
A6: Latin America | G6: yellow highlight = <300k
A7: BonAg | B7: Argentina | C7: Integrated crop producer | D7: Soybean, Corn, Citrus, Wheat | E7: — (not a food company) | F7: — | G7: =H7*0.8*2*3*7.5 -> 5400000 | H7: 150000 | I7: MOU signed. Argentine market-opener. Diversified row crop and citrus operations. May provide access to farms of Cresud (to validate)
A8: L4 — Defining Contract
A9: No companies at this stage currently
A10: L3 — Qualifying Opportunity
A11: Latin America
A12: Peruvian Market | B12: Peru | C12: Market-opener | D12: Table Grapes | E12: — | F12: — | G12: unknown | H12: unknown | I12: NDA circulated, business case in progress. Technical Advisor contact. LatAM grape market-opener.
A13: L2 — Our Active Engagements
A14: North America
A15: Dole plc | B15: Ireland | C15: Integrated produce company | D15: Bananas, Pineapples, Berries, Fresh Vegetables | E15: 4.7 | F15: 1 | G15: =H15*0.8*2*3*7.5 -> 1602000 | H15: 44500 | I15: World's largest fresh produce company. 110,000 acres. $8.5B revenue. Source: Dole plc 2024 Annual Report.
A16: Driscoll's | B16: USA | C16: Berry producer/marketer | D16: Strawberries, Raspberries, Blueberries, Blackberries | E16: 4.45 | F16: 1 | G16: =H16*0.8*2*3*7.5 -> 576000 | H16: 16000 | I16: World's largest berry company. 900+ growers, 20+ countries. Source: Driscoll's company information.
A17: Fresh Del Monte Produce | B17: USA | C17: Integrated fresh produce | D17: Bananas, Pineapples, Melons, Vegetables | E17: 4.15 | F17: 1 | G17: =H17*0.8*2*3*7.5 -> 1368000 | H17: 38000 | I17: Plantations in Costa Rica, Guatemala, Kenya, Philippines. Source: Fresh Del Monte Annual Report.
A18: PepsiCo | B18: USA | C18: Global food & beverage | D18: Potato, Corn, Citrus | E18: — | F18: — | G18: =H18*0.8*2*3*7.5 -> 4320000 | H18: 120000 | I18: Pitch deck sent. Major buyer with strong contract farming programmes across multiple continents.
A19: Western Europe
A20: Unifrutti Group | B20: Italy | C20: Integrated fresh produce | D20: Bananas, Grapes, Apples, Citrus | E20: 3.95 | F20: 2 | G20: =H20*0.8*2*3*7.5 -> 432000 | H20: 12000 | I20: Pitch deck sent. Farms in Chile, Philippines, Ecuador, Turkey, Italy. Source: Unifrutti.
A21: Fyffes | B21: Ireland | C21: Integrated fresh produce | D21: Bananas, Melons, Pineapples | E21: 3.8 | F21: 2 | G21: =H21*0.8*2*3*7.5 -> 360000 | H21: 10000 | I21: First message sent. Owned by Sumitomo. Farms in Central America. Source: Fyffes.
A22: BAT (British American Tobacco) | B22: UK | C22: Integrated tobacco producer | D22: Tobacco Leaf | E22: — | F22: — | G22: =H22*0.8*2*3*7.5 -> 3240000 | H22: 90000 | I22: Pitch deck sent. ~90,000 ha contracted tobacco globally. Strong agronomic oversight.
A23: Philip Morris International | B23: Switzerland | C23: Integrated tobacco producer | D23: Tobacco Leaf | E23: — | F23: — | G23: =H23*0.8*2*3*7.5 -> 7200000 | H23: 200000 | I23: Outreach via David's network. ~200,000 ha contracted. Strong sustainability programmes.
A24: SLM Partners | B24: Ireland | C24: Regenerative farmland investment manager | D24: Organic Row Crops (US), Almonds, Walnuts, Olives (Iberia), Mixed Crops (Australia) | E24: — | F24: — | G24: =H24*0.8*2*3*7.5 -> 828000 | H24: 23000 | I24: $760m AUM. 300,000 ha total under management globally. Crop/perennial land: ~15,000 ha US Midwest organic row crops, ~3,000 ha Iberian nut/olive orchards, ~5,000 ha AU mixed cropland. Excludes ~200K ha AU rangeland and Irish forestry. Source: SLM Partners Impact Report 2024.
A25: Agrifirm | B25: Netherlands | C25: Agricultural cooperative | D25: Arable crops, Horticulture inputs | E25: — | F25: — | G25: =H25*0.8*2*3*7.5 -> 360000 | H25: 10000 | I25: 10k addressable hectares. Note: already uses competing biostimulant. ~10,000 NL arable members.
A26: Associated British Foods | B26: UK | C26: Diversified food & retail | D26: Sugar (Beet/Cane), Wheat | E26: 3.35 | F26: 2 | G26: =H26*0.8*2*3*7.5 -> 2700000 | H26: 75000 | I26: Pitch deck sent. Illovo Sugar: 75K+ ha sugarcane across 6 African nations. British Sugar: 3,000+ UK growers. £17.3B group revenue. Source: ABF Annual Report 2025.
A27: Bakkerij Borgesius | B27: Netherlands | C27: Industrial bakery | D27: Wheat (flour buyer) | E27: — | F27: — | G27: =H27*0.8*2*3*7.5 -> 0 | H27: 0 | I27: Valentin initial engagement — handed to Sophia. Dutch bakery (est. 1895), supplies 80%+ of NL households. No direct farmland — flour/wheat buyer. Limited Stimblue+ fit unless via grower supply chain.
A28: Ferrero Group | B28: Italy | C28: Integrated confectionery / hazelnut producer | D28: Hazelnuts, Cocoa, Palm Oil, Sugar | E28: 4.25 | F28: 1 | G28: =H28*0.8*2*3*7.5 -> 360000 | H28: 10000 | I28: €18.4B group revenue (FY2024). Hazelnut Company owns agrifarms in Chile (~5,000 ha), Australia (~2,000 ha), Argentina, Georgia, Serbia. 7 processing plants. World's largest hazelnut buyer (~25% global supply). Source: Ferrero Key Figures / Hazelnut Charter 2024.
A29: Oceania
A30: Zespri International | B30: New Zealand | C30: Kiwifruit marketer (cooperative) | D30: Kiwifruit (Green, Gold, Red) | E30: 4.5 | F30: 1 | G30: =H30*0.8*2*3*7.5 -> 486000 | H30: 13500 | I30: World's largest kiwifruit marketer. ~13,500 ha in NZ. Source: Zespri Annual Report 2024.
A31: T&G Global | B31: New Zealand | C31: Integrated fresh produce | D31: Apples (Jazz, Envy), Tomatoes, Berries | E31: 4.3 | F31: 1 | G31: =H31*0.8*2*3*7.5 -> 126000 | H31: 3500 | I31: Reached out 02.03.2026. Proprietary apple varieties. Source: T&G Global Annual Report.
A32: Africa
A33: Nigerian Market | B33: Nigeria | C33: Market-opener | D33: Diverse (tropical) | E33: — | F33: — | G33: unknown | H33: unknown | I33: Second call with Obi. West African market entry opportunity.
A34: L1 — Our Next Targets
A35: North America
A36: Wonderful Company | B36: USA | C36: Integrated nut/citrus producer | D36: Pistachios, Almonds, Pomegranates, Citrus, Mandarins | E36: 4.8 | F36: 1 | G36: =H36*0.8*2*3*7.5 -> 1440000 | H36: 40000 | I36: ~90,000 acres in CA. World's largest pistachio/almond grower. Source: Wonderful Orchards.
A37: Stemilt Growers | B37: USA | C37: Integrated tree fruit producer | D37: Apples, Cherries, Pears | E37: 4.6 | F37: 1 | G37: =H37*0.8*2*3*7.5 -> 216000 | H37: 6000 | I37: Major WA State tree fruit grower. Family-owned. Source: Stemilt company information.
A38: CMI Orchards | B38: USA | C38: Integrated apple producer | D38: Apples (Ambrosia, Kanzi, KIKU) | E38: 4.6 | F38: 1 | G38: =H38*0.8*2*3*7.5 -> 180000 | H38: 5000 | I38: Major apple grower/marketer. Proprietary varieties. Source: CMI Orchards.
A39: Mastronardi Produce (SUNSET) | B39: Canada | C39: Greenhouse vegetable producer | D39: Tomatoes, Peppers, Cucumbers (greenhouse) | E39: 4.6 | F39: 1 | G39: =H39*0.8*2*3*7.5 -> 10800 | H39: 300 | I39: Major greenhouse producer (SUNSET brand). ON, MI, Mexico. Source: Mastronardi.
A40: NatureFresh Farms | B40: Canada | C40: Greenhouse produce producer | D40: Tomatoes, Peppers, Cucumbers (greenhouse) | E40: 4.55 | F40: 1 | G40: =H40*0.8*2*3*7.5 -> 7200 | H40: 200 | I40: Large greenhouse vegetable producer. Multiple NA facilities. Source: NatureFresh.
A41: Windset Farms | B41: Canada | C41: Greenhouse produce producer | D41: Tomatoes, Peppers, Cucumbers (greenhouse) | E41: 4.55 | F41: 1 | G41: =H41*0.8*2*3*7.5 -> 6480 | H41: 180 | I41: Major greenhouse company. BC, CA, Mexico. Source: Windset Farms.
A42: Grimmway Farms | B42: USA | C42: Integrated carrot/vegetable producer | D42: Carrots, Organic Vegetables | E42: 4.5 | F42: 1 | G42: =H42*0.8*2*3*7.5 -> 720000 | H42: 20000 | I42: World's largest carrot producer. 50,000+ acres. Cal-Organic brand. Source: Grimmway.
A43: Blue Diamond Growers | B43: USA | C43: Almond cooperative | D43: Almonds | E43: 4.45 | F43: 1 | G43: =H43*0.8*2*3*7.5 -> 6480000 | H43: 180000 | I43: World's largest almond processor. ~3,000 CA growers. Source: Blue Diamond.
A44: Limoneira | B44: USA | C44: Integrated citrus/avocado producer | D44: Lemons, Avocados, Oranges | E44: 4.4 | F44: 1 | G44: =H44*0.8*2*3*7.5 -> 144000 | H44: 4000 | I44: ~10,000 acres in CA. Premium lemon producer. Source: Limoneira Annual Reports.
A45: Bolthouse Farms | B45: USA | C45: Integrated carrot/beverage producer | D45: Carrots, Beverages | E45: 4.35 | F45: 1 | G45: =H45*0.8*2*3*7.5 -> 288000 | H45: 8000 | I45: Major carrot producer (Butterfly Equity). Source: Bolthouse Farms.
A46: Tanimura & Antle | B46: USA | C46: Integrated lettuce/vegetable producer | D46: Lettuce, Romaine, Celery, Broccoli, Cauliflower | E46: 4.35 | F46: 1 | G46: =H46*0.8*2*3*7.5 -> 522000 | H46: 14500 | I46: Major Salinas Valley grower. 36,000+ acres. Source: Tanimura & Antle.
A47: Duda Farm Fresh Foods | B47: USA | C47: Integrated vegetable producer | D47: Celery, Lettuce, Radishes, Citrus | E47: 4.3 | F47: 1 | G47: =H47*0.8*2*3*7.5 -> 432000 | H47: 12000 | I47: Major US grower in FL, CA, AZ. Family-owned since 1926. Source: Duda.
... A61: TreeTop | B61: USA | C61: Apple cooperative | D61: Apples, Pears | E61: 3.8 | F61: 2 | G61: =H61*0.8*2*3*7.5 -> 504000 | H61: 14000 | I61: Apple cooperative in WA. ~1,100 members. Source: TreeTop.
A62: Latin America
A63: San Miguel Global | B63: Chile | C63: Integrated fruit producer | D63: Grapes, Citrus, Berries, Stone Fruits, Apples | E63: 4.55 | F63: 1 | G63: =H63*0.8*2*3*7.5 -> 648000 | H63: 18000 | I63: Major integrated fruit company. Farms across hemispheres. Source: San Miguel.
A64: Hortifrut | B64: Chile | C64: Integrated berry producer | D64: Blueberries, Raspberries, Blackberries, Strawberries | E64: 4.55 | F64: 1 | G64: =H64*0.8*2*3*7.5 -> 540000 | H64: 15000 | I64: World's largest berry producer. Global farms. Source: Hortifrut Annual Reports.
A65: Camposol | B65: Peru | C65: Integrated fresh produce | D65: Avocados, Blueberries, Grapes, Mandarins | E65: 4.4 | F65: 1 | G65: =H65*0.8*2*3*7.5 -> 900000 | H65: 25000 | I65: Peru's largest agri exporter. 25,000+ ha. $184M EBITDA 2024. Source: Camposol 2024.
A66: Agricola Garces | B66: Chile | C66: Integrated fruit producer | D66: Cherries, Grapes, Blueberries, Apples | E66: 4.2 | F66: 1 | G66: =H66*0.8*2*3*7.5 -> 180000 | H66: 5000 | I66: Major Chilean fruit producer. Premium fruit for Asian markets. Source: Agricola Garces.
A67: Agroberries | B67: Chile | C67: Integrated berry producer | D67: Blueberries, Cherries | E67: 4.2 | F67: 1 | G67: =H67*0.8*2*3*7.5 -> 108000 | H67: 3000 | I67: Chilean berry producer in Chile and Peru. Source: Agroberries.
A68: Adecoagro | B68: Luxembourg | C68: Integrated agribusiness | D68: Sugar Cane, Grains, Rice | E68: 3.85 | F68: 2 | G68: =H68*0.8*2*3*7.5 -> 8280000 | H68: 230000 | I68: ~230,000 ha in Argentina, Brazil, Uruguay. Source: Adecoagro Annual Reports.
A69: SLC Agrícola | B69: Brazil | C69: Large-scale crop producer | D69: Soybeans, Cotton, Corn | E69: 3.8 | F69: 2 | G69: =H69*0.8*2*3*7.5 -> 26424000 | H69: 734000 | I69: Brazil's largest farmer. ~734,000 ha planted 2024/25. Source: SLC Agrícola 2024 Report.
A70: Africa
A71: Westfalia Fruit | B71: South Africa | C71: Integrated avocado/fruit producer | D71: Avocados, Mangoes, Litchis | E71: 4.4 | F71: 1 | G71: =H71*0.8*2*3*7.5 -> 432000 | H71: 12000 | I71: World leader in avocados. Farms in SA, Chile, Peru, Colombia, Mozambique. Source: Westfalia.
A72: Capespan | B72: South Africa | C72: Fresh produce exporter | D72: Citrus, Grapes, Apples, Pears, Stone Fruits | E72: 3.4 | F72: 2 | G72: =H72*0.8*2*3*7.5 -> 288000 | H72: 8000 | I72: Major SA fruit exporter. Source: Capespan.
A73: Western Europe
A74: BerryWorld | B74: UK | C74: Berry marketer/genetics | D74: Strawberries, Raspberries, Blueberries, Blackberries | E74: 4.1 | F74: 1 | G74: =H74*0.8*2*3*7.5 -> 144000 | H74: 4000 | I74: Berry genetics company. Proprietary varieties. UK/EU. Source: BerryWorld.
A75: Greenyard | B75: Belgium | C75: Fresh produce supplier | D75: Fresh Fruits, Vegetables, Frozen Produce | E75: 3.8 | F75: 2 | G75: =H75*0.8*2*3*7.5 -> 180000 | H75: 5000 | I75: Major EU fresh produce supplier. EU biostimulant-friendly. Source: Greenyard.
A76: Florette (Agrial) | B76: France | C76: Fresh salad producer | D76: Salads, Leafy Greens, Fresh-cut Vegetables | E76: 3.8 | F76: 2 | G76: =H76*0.8*2*3*7.5 -> 216000 | H76: 6000 | I76: EU leader in fresh salads. Part of Agrial cooperative. Source: Agrial/Florette.
A77: Associated British Foods | B77: UK | C77: Diversified food & retail | D77: Sugar (Beet/Cane), Wheat | E77: 3.35 | F77: 2 | G77: =H77*0.8*2*3*7.5 -> 2700000 | H77: 75000 | I77: Illovo Sugar: 75K+ ha Africa. Source: ABF / Illovo Annual Reports.
A78: Southeast Asia
A79: Olam Group | B79: Singapore | C79: Integrated agribusiness | D79: Cocoa, Coffee, Nuts, Spices, Cotton, Rice | E79: 4.2 | F79: 1 | G79: =H79*0.8*2*3*7.5 -> 25200000 | H79: 700000 | I79: 700,000+ ha global. Almond orchards, coffee estates, cocoa farms. Source: Olam Annual Reports.
A80: Oceania
A81: Costa Group | B81: Australia | C81: Integrated fresh produce | D81: Berries, Tomatoes, Avocados, Citrus | E81: 4.8 | F81: 1 | G81: =H81*0.8*2*3*7.5 -> 288000 | H81: 8000 | I81: Now Paine Schwartz/Driscoll's/BCI consortium. ~8,000 ha. Source: Costa Group / BCI 2024.
A82: Seeka | B82: New Zealand | C82: Integrated kiwifruit/avocado | D82: Kiwifruit, Avocados | E82: 4.25 | F82: 1 | G82: =H82*0.8*2*3*7.5 -> 126000 | H82: 3500 | I82: Major NZ grower and post-harvest operator. Source: Seeka Annual Reports.
A84: Summary
A85: Total Companies | B85: 63
A86: Tier 1 Targets | B86: 41
A87: Tier 2 Targets | B87: 17
A88: Unscored (new leads) | B88: 5
A89: Total Addressable Hectares | B89: 3,727,310
A90: Revenue Model | B90: Ha × 80% × 2 L/app × 3 apps/yr × €7.50/L

Sheet Current Leads & Contacts
A1: Current Leads & Contacts
A2: Company Name | C2: Current Status | D2: Contact | E2: Position | F2: Email Address | G2: LinkedIn | H2: Region | I2: Crops | J2: Matrix Score | K2: Tier | L2: Matrix reason | M2: KB Owner
A3: L5: Under contract | B3: Revenue target ($7.5/L)
A4: Bonag | B4: US$12m by 2030 | C4: MOU signed | D4: Roberto Aguerra | E4: Co-Founder | F4: raguirre@bon-ag.com | H4: Argentina | I4: Soybean, Corn, Citrus, Wheat | J4: NA | L4: Market-opener | M4: David
A5: L4: Defining Contract
A7: L3: Qualifying opportunity
A8: Peruvian market | B8: TBD | C8: NDA circulated, business case in progress | D8: Oscar Segaldo | E8: Technical Advisor | H8: LatAM | I8: Grapes | L8: Market-opener | M8: David
A9: L2: Active Initial engagement
A10: Unifrutti Group | B10: =18000*4*8 -> 576000 | C10: Pitch deck sent. Touch base end of next week. | D10: Rachel Pope | E10: Board member | I10: Diverse Fruits | J10: 3.95 | K10: 2 | M10: David
A11: SLM Partners | B11: TBD | C11: First meeting scheduled for trial engagement in Iberia | D11: Joao Roseiro | E11: Agronomy Director
A12: Agrifirm | B12: TBD | C12: 10k addressable hectares. But already have Biostim. | D12: Josein
A13: PepsiCo | B13: TBD | C13: Pitch deck sent to Vahid. Call on Tuesday | D13: Vahid Monadjem | E13: Selling to them | F13: vahidjm@gmail.com | I13: Potato, Corn, Citrus | J13: TEST. | M13: David
A14: British Fruits | B14: TBD | C14: Pitch deck sent to Vahid. Call on Tuesday | D14: Vahid Monadjem | F14: vahidjm@gmail.com | J14: TEST. | M14: David
A15: Zespri | B15: 284000 | C15: Mapping revenue | D15: Felicity | H15: New Zealand | I15: Kiwi | M15: David
A16: Philip Morris International | C16: Outreach made - David's network.
A17: BAT | B17: $1.8m | C17: Pitch deck sent to Head of Innovation | D17: Rishad Sharif | E17: Group Head of Quality & Operations | H17: UK, Global | I17: Tabacco Leaf | M17: David
A19: Liberia / Kenya / Zimbabwean market | B19: tbd | C19: first call | D19: Funke Michales
A20: Nigeria | B20: tbd | C20: Second call | D20: Obi
A21: Fyffes | B21: tbd | C21: first message sent. | D21: Julie Cornouyer | E21: Director of Global Sustainability
A22: Dole International | C22: In progress | D22: Minerva G. Nuñez, Ph.D. | E22: Senior Research Scientist | H22: Philipines | M22: Sophia
A23: Dole Phillipines (Stanfilco Div.) | C23: Stalled | D23: Ariel B. Bolledo | E23: Research and Development | H23: Philipines | M23: Sophia
A24: T&G Global | C24: Reached out 02.03.2026 | D24: Jemma Whiten
A25: Fresh Del Monte Produce Inc. | C25: 1000s
A26: Borgesuis | C26: Valentin initial enagement - handed to Sophia - awaiting response
A27: Driscolls | C27: done
A28: L1: Our next tranche
A29: Olam Food Ingredients (OFI)
A30: Growers United (coop) | D30: Michiel Kemmer | H30: Netherlands | L30: not integrated, co-op | M30: Sophia
A31: Blue Diamond Growers | C31: to do
A32: Chiquita | C32: Juan-Carlos has contacts. Need to work with him to understand trialling to deal pipeline
A33: Greenyard
A34: Costa Group | C34: Reached out to Australian contact. No for now | J34: TEST. | M34: David
A35: Barry Callebaut | C35: done. large cocoa trader | G35: https://www.linkedin.com/in/paul-antoine-hourticq/
A36: WHF | C36: done outreach
A37: Camposol | I37: Avocados, Blueberries, Grapes, Mandarins, Shrimp
A38: Hortifrut | I38: Hortifrut
A43: L0: No
A45: General Mills | C45: done - no response
A46: McCain | C46: done - no response
A47: Bonduelle | C47: done - no response
A48: Fyffes | C48: done - no response. follow up another avenue | D48: Julie Cornoyer | H48: Fyffes | I48: Fruits. Banana, Melon | L48: Integrated | M48: Sophia
A51: Kelp Blue old existing contacts
C52: Dolefil | F52: Francis Babac | G52: Director | H52: Francis.Babac@doleinyl.com | O52: Anthony --> Sophia
F53: Novy Castolo | G53: Operation Manager | H53: Novy.Castolo@doleintl.com | O53: Anthony --> Sophia
D54: Jeanette Abalde | E54: QA Superintendend | F54: Jeanette.Abalde@dolefil.com | M54: Anthony --> Sophia
D55: Dr.Reofeli Perez | E55: Sr. Scientist | F55: reofeli.perez@doleintl.com | M55: Anthony --> Sophia
D56: Dr. Roel Dayondon | E56: Sr. Scientist | F56: Roel.Dayodon@doleintl.com | M56: Anthony --> Sophia
D57: Elvie Escalicas | E57: Despatching In-charge | F57: Elvie.Escalicas@doleintl.com | M57: Anthony --> Sophia
A58: Dole Stanfilco | D58: Dr. Gaudencia Lantican | E58: Sr. Scientist | I58: Durian | M58: Anthony --> Sophia
D59: Ariel Bolledo | E59: Sr. Scientist | F59: Ariel.Bolledo@doleintl.com | M59: Anthony --> Sophia
A60: Del Monte Phil Inc. | D60: Analiza Tagle | E60: Sr. Scientist | F60: TagleAG@delmonte-phil.com | I60: Pineapple | M60: Anthony --> Sophia
D61: Hans Mahilom | E61: Research in charge fruit protection | F61: MahilumHA@delmonte-phil.com | I61: Pineapple | M61: Anthony --> Sophia
D62: Resheilo Ordoyo | E62: Research in charge fruit protection | F62: OrdoyoRF@delmonte-phil.com | I62: Pineapple | M62: Anthony --> Sophia
A63: Del Monte Fresh Produce | D63: Dr. Nicole Magculia | E63: Sr. Manager Research | F63: Nmagculia@Freshdelmonte.com | I63: Pine and Banana | M63: Anthony --> Sophia
D64: Richard Apas | E64: Manager Postharvest Research | F64: Rapas@Freshdelmonte.com | M64: Anthony --> Sophia
D65: Rene Orias | E65: Sr. Manager for Purchasing | F65: Rorias@Freshdelmonte.com | M65: Anthony --> Sophia
D66: Cristian Alvarado | E66: Sr. Director QA/FS APAC | F66: CAlvarado1@Freshdelmonte.com | M66: Anthony --> Sophia
A67: Lapanday Foods Co. | D67: Dr. Joey Orajay | E67: Manager Research Department | F67: jiorajay@lapanday.com | M67: Anthony --> Sophia
D68: Romeo Mugas | E68: Researcher Postharvest | F68: romeomugasjr100991@gmail.com | M68: Anthony --> Sophia
D69: Sheryl Quiruben | E69: Plt. nutrition reasercher | I69: Banana | M69: Anthony --> Sophia
D70: Aprilyn Regner | E70: Plant Pathology and Etomology Research head | I70: Banana | M70: Anthony --> Sophia
D71: Marites Celiz | E71: Tissue Culture Laboratory in charge | I71: Banana Tissue Laboratory | M71: Anthony --> Sophia
A72: Lapanday Diversified Product Co. | D72: Patrick Porter | E72: Farm Manager | F72: paporter@lapanday.com | I72: Pineapple | M72: Anthony --> Sophia
A73: Alcantara | D73: Mencho Loayan | E73: Techincal Support Department Manager (Pineapple) | F73: mmloayan@saranganibay.com.ph | M73: Anthony --> Sophia
D74: Mae Lao | E74: Techincal Support Department Manager (Banana) | I74: Banana | M74: Anthony --> Sophia
A75: Natures Fresh | D75: Mike Butron | E75: Plantation Manager | I75: Pineapple | M75: Anthony --> Sophia
A76: Tadeco | D76: Marlo Bathan | E76: Assistant Manager, Plant Nutrition Research | I76: Pomelo | M76: Anthony --> Sophia
D77: Marchie Macabodbod | E77: Superintendent, Postharvest Research | I77: Banana | M77: Anthony --> Sophia
A78: Sumifru | D78: Joseph Balandra | E78: Pineapple Plantaion Manager | F78: joseph.balndra@sumifru.com | I78: Pineapple | M78: Anthony --> Sophia
D79: Kesha Mae Balagagno | E79: Tissue Culture Laboratory in charge | I79: Tissue Laboratory | M79: Anthony --> Sophia
A80: Unifrutti Phil | D80: Mark Valero | E80: Soils and Plant Nutrition Supervisor | M80: Anthony --> Sophia
A81: Hijo Resource Co. | D81: Giovanni Zanoria | E81: Production Head | I81: Banana | M81: Anthony --> Sophia
A82: SODACO | D82: Mario Magbanua | E82: Farm Manager | F82: mr.magbanua@gmail.com | I82: Pomelo | M82: Anthony --> Sophia
A83: Eng Seng Food Product | D83: Ruby Bernales | E83: Manager | F83: rubygudito@gmail.com | I83: Durian | M83: Anthony --> Sophia
A84: BJM Durian Exporter | D84: Bill | E84: Plant in charge | I84: Durian | M84: Anthony --> Sophia
A85: Maylong Enterprise | D85: Jovelyn | E85: Admin in charge | I85: Durian | M85: Anthony --> Sophia
A86: Mei He-Plus | D86: Anna Rose Into | E86: Admin in charge | I86: Durian | M86: Anthony --> Sophia
A87: XLG Durian Exporter | D87: Merafe Co | E87: Plant Manager | F87: meerafeco@gmail.com | I87: Durian | M87: Anthony --> Sophia
A88: Menzi Pomelo | D88: Alexander Ines | E88: Farm in charge | I88: Pomelo | M88: Anthony --> Sophia
A89: Golden Pomelo | D89: Nilo Ramiso | E89: Farm Manager | I89: Pomelo | M89: Anthony --> Sophia
A90: Vic Pomelo | D90: Kobi Tan | E90: Owner | I90: Pomelo | M90: Anthony --> Sophia
A91: Nakashin Davao (Mango Exporter) | D91: Efraim Gloriba | E91: Raw Material Procurement Officer | F91: efraim.gloriba@nakashin.com.ph | I91: Mango | M91: Anthony --> Sophia
A92: CM Farm | D92: Pocholo dela Pena | E92: Owner | I92: Mango | M92: Anthony --> Sophia
A93: Argan Dragon Fruit Farm | D93: Andy | E93: Admin in charge | I93: Dragon Fruit | M93: Anthony --> Sophia
A94: Sia Farm | D94: Ramil Sia | E94: Owner | I94: Dragon Fruit | M94: Anthony --> Sophia

Sheet 5 Ls
A1: Level | B1: Definition | C1: Evidence Required
A2: L1 — Identified | B2: Target mapped, no meaningful contact | C2: Research complete, entry point identified, cold call initiated
A3: L2 — Engaged | B3: Conversation initiated, interest signal | C3: Meeting held or response received
A4: L3 — Qualifying | B4: Mutual interest confirmed, scope discussed, target revenue identified | C4: Defined next step, internal champion identified
A5: L4 — Advancing | B5: Active negotiation or commercial discussion to sign engagement | C5: Term sheet / MOU / trial agreement in motion
A6: L5 — Executing | B6: Actually managing execution of the contract to reach revenue targets
A8: NEW:
A9: L5 — Under Contract | B9: Commercial agreement executed; actively managing delivery against revenue targets. | C9: Signed MOU/contract; revenue milestones defined; delivery schedule in place.
A10: L4 — Defining Contract | B10: Commercial terms under negotiation; mutual commitment to formalise engagement. | C10: Term sheet, MOU, or trial agreement in active drafting or review.
A11: L3 — Qualifying Opportunity | B11: Mutual interest confirmed; scope, fit, and target revenue under discussion. | C11: Defined next steps; internal champion identified; business case in progress.
A12: L2 — Active Engagement | B12: Dialogue initiated; early signals of interest or strategic fit being explored. | C12: Meeting held or pitch delivered; follow-up response received.
A13: L1 — Identified Target | B13: Company mapped and assessed; no meaningful commercial contact yet established. | C13: Research complete; entry point identified; outreach planned or initiated.

Sheet Matrix - Top 50 companies
A1: Decision Matrix - Target Partners (Group - Top 50 food companies globally)
A2: Scores are 0–5. Weighted score and tier update automatically based on Assumptions tab.
A4: Company | B4: HQ Country | C4: Region | D4: Business Type (eg. integrated producer) | E4: Countries with controlled farms | F4: Main crops (top 5) | G4: Integration / Owns Land (0–5) | H4: High-Value Crop Exposure (0–5) | I4: Registration Ease (0–5) | J4: Scale Potential (0–5) | K4: Strategic Leverage (0–5) | L4: Penalty: Complexity (0–-2) | M4: Weighted Score (0–5) | N4: Tier | O4: Owner | P4: Notes / Evidence
A5: Top 50 food companies in the world
A6: Ahold Delhaize | B6: Netherlands | C6: =IFERROR(VLOOKUP(B6,Lists!$A$2:$B$200,2,FALSE()),"Europe") -> Europe | D6: Retail/supermarket chain | E6: Netherlands, Belgium, USA (limited direct farm control) | F6: Vegetables, Fruits, Dairy (sourced, not owned) | G6: 1 | H6: 3 | I6: 4 | J6: 2 | K6: 4 | L6: -1 | M6: =IFERROR((G6*Assumptions!$B$5 + H6*Assumptions!$B$6 + I6*Assumptions!$B$7 + J6*Assumptions!$B$8 + K6*Assumptions!$B$9 + L6*Assumptions!$B$10),"" ) -> 2.25 | N6: =IF(M6="","",IF(M6>=Assumptions!$B$14,"Tier 1",IF(M6>=Assumptions!$B$15,"Tier 2",IF(M6>=Assumptions!$B$16,"Tier 3","Tier 4")))) -> Tier 4 | P6: Major European retailer with US presence (Food Lion, Giant, Stop & Shop). Sustainable sourcing programs but limited direct land control. Primary focus on retail, not farming. Source: Company annual reports, sustainability reports.
A7: Nestlé | B7: Switzerland | C7: =IFERROR(VLOOKUP(B7,Lists!$A$2:$B$200,2,FALSE()),"Europe") -> Europe | D7: Global food & beverage manufacturer | E7: Côte d'Ivoire, Ghana, Vietnam, Indonesia, Brazil (cocoa/coffee programs) | F7: Coffee, Cocoa, Dairy, Cereals, Vegetables | G7: 2 | H7: 4 | I7: 4 | J7: 5 | K7: 5 | L7: -2 | M7: =IFERROR((G7*Assumptions!$B$5 + H7*Assumptions!$B$6 + I7*Assumptions!$B$7 + J7*Assumptions!$B$8 + K7*Assumptions!$B$9 + L7*Assumptions!$B$10),"" ) -> 3.85 | N7: =IF(M7="","",IF(M7>=Assumptions!$B$14,"Tier 1",IF(M7>=Assumptions!$B$15,"Tier 2",IF(M7>=Assumptions!$B$16,"Tier 3","Tier 4")))) -> Tier 2 | P7: World's largest food company. Nescafé Plan, Cocoa Plan programs involve direct farmer relationships but limited owned land. Strong sustainability commitments. Very complex procurement across 180+ countries. Source: Nestlé Annual Review, Creating Shared Value reports.
A8: JBS N.V. | B8: Brazil | C8: =IFERROR(VLOOKUP(B8,Lists!$A$2:$B$200,2,FALSE()),"Latin America") -> Latin America | D8: Vertically integrated protein processor | E8: Brazil, USA, Australia, Argentina (cattle, poultry operations) | F8: Beef, Poultry, Pork, Animal feed (corn, soy) | G8: 4 | H8: 2 | I8: 3 | J8: 5 | K8: 4 | L8: -1 | M8: =IFERROR((G8*Assumptions!$B$5 + H8*Assumptions!$B$6 + I8*Assumptions!$B$7 + J8*Assumptions!$B$8 + K8*Assumptions!$B$9 + L8*Assumptions!$B$10),"" ) -> 3.9 | N8: =IF(M8="","",IF(M8>=Assumptions!$B$14,"Tier 1",IF(M8>=Assumptions!$B$15,"Tier 2",IF(M8>=Assumptions!$B$16,"Tier 3","Tier 4")))) -> Tier 2 | P8: World's largest meat processor. Owns feedlots, processing plants globally. JBS USA (Pilgrim's Pride, Swift). Focus on protein, limited crop-specific biostimulant application. Source: JBS Annual Reports, SEC filings.
A9: Archer Daniels Midland (ADM) | B9: USA | C9: =IFERROR(VLOOKUP(B9,Lists!$A$2:$B$200,2,FALSE()),"North America") -> North America | D9: Agricultural commodity trader/processor | E9: USA, Brazil, Argentina, Ukraine (extensive grain sourcing) | F9: Corn, Soybeans, Wheat, Oilseeds, Barley | G9: 2 | H9: 1 | I9: 3 | J9: 5 | K9: 4 | L9: -1 | M9: =IFERROR((G9*Assumptions!$B$5 + H9*Assumptions!$B$6 + I9*Assumptions!$B$7 + J9*Assumptions!$B$8 + K9*Assumptions!$B$9 + L9*Assumptions!$B$10),"" ) -> 3 | N9: =IF(M9="","",IF(M9>=Assumptions!$B$14,"Tier 1",IF(M9>=Assumptions!$B$15,"Tier 2",IF(M9>=Assumptions!$B$16,"Tier 3","Tier 4")))) -> Tier 3 | P9: Major commodity trader and processor. Does not own significant farmland - works with independent farmers/cooperatives. Focus on commodity grains. Biostimulant potential limited by crop type. Source: ADM Annual Reports, investor presentations.
A10: Sysco | B10: USA | C10: =IFERROR(VLOOKUP(B10,Lists!$A$2:$B$200,2,FALSE()),"North America") -> North America | D10: Foodservice distribution | E10: USA, Canada, UK, Ireland (no direct farm control) | F10: All categories (sourced from suppliers) | G10: 0 | H10: 3 | I10: 4 | J10: 1 | K10: 3 | L10: 0 | M10: =IFERROR((G10*Assumptions!$B$5 + H10*Assumptions!$B$6 + I10*Assumptions!$B$7 + J10*Assumptions!$B$8 + K10*Assumptions!$B$9 + L10*Assumptions!$B$10),"" ) -> 1.45 | N10: =IF(M10="","",IF(M10>=Assumptions!$B$14,"Tier 1",IF(M10>=Assumptions!$B$15,"Tier 2",IF(M10>=Assumptions!$B$16,"Tier 3","Tier 4")))) -> Tier 4 | P10: Largest foodservice distributor in North America. No direct farming operations - sources from suppliers. Could influence supplier practices through specifications. Source: Sysco Annual Reports, sustainability reports.
A11: Performance Food Group | B11: USA | C11: =IFERROR(VLOOKUP(B11,Lists!$A$2:$B$200,2,FALSE()),"North America") -> North America | D11: Foodservice distribution | E11: USA (no direct farm control) | F11: All categories (sourced from suppliers) | G11: 0 | H11: 3 | I11: 4 | J11: 1 | K11: 2 | L11: 0 | M11: =IFERROR((G11*Assumptions!$B$5 + H11*Assumptions!$B$6 + I11*Assumptions!$B$7 + J11*Assumptions!$B$8 + K11*Assumptions!$B$9 + L11*Assumptions!$B$10),"" ) -> 1.4 | N11: =IF(M11="","",IF(M11>=Assumptions!$B$14,"Tier 1",IF(M11>=Assumptions!$B$15,"Tier 2",IF(M11>=Assumptions!$B$16,"Tier 3","Tier 4")))) -> Tier 4 | P11: Third-largest foodservice distributor in US. Pure distribution model. No farming operations. Source: PFG Annual Reports.
A12: Bunge Global SA | B12: USA | C12: =IFERROR(VLOOKUP(B12,Lists!$A$2:$B$200,2,FALSE()),"North America") -> North America | D12: Agricultural commodity trader/processor | E12: Brazil, Argentina, USA, Europe (extensive sourcing) | F12: Soybeans, Corn, Wheat, Canola, Sunflower | G12: 2 | H12: 1 | I12: 3 | J12: 5 | K12: 4 | L12: -1 | M12: =IFERROR((G12*Assumptions!$B$5 + H12*Assumptions!$B$6 + I12*Assumptions!$B$7 + J12*Assumptions!$B$8 + K12*Assumptions!$B$9 + L12*Assumptions!$B$10),"" ) -> 3 | N12: =IF(M12="","",IF(M12>=Assumptions!$B$14,"Tier 1",IF(M12>=Assumptions!$B$15,"Tier 2",IF(M12>=Assumptions!$B$16,"Tier 3","Tier 4")))) -> Tier 3 | P12: Major commodity trader (part of ABCD group). Works with farmers through origination networks but limited owned production. Focus on commodity grains/oilseeds. Source: Bunge Annual Reports.
A13: Unilever | B13: UK | C13: =IFERROR(VLOOKUP(B13,Lists!$A$2:$B$200,2,FALSE()),"Europe") -> Europe | D13: Consumer goods manufacturer | E13: Indonesia, India, Brazil, EU (sustainable sourcing programs) | F13: Palm oil, Tea, Cocoa, Soybeans, Vegetables | G13: 2 | H13: 3 | I13: 4 | J13: 4 | K13: 5 | L13: -2 | M13: =IFERROR((G13*Assumptions!$B$5 + H13*Assumptions!$B$6 + I13*Assumptions!$B$7 + J13*Assumptions!$B$8 + K13*Assumptions!$B$9 + L13*Assumptions!$B$10),"" ) -> 3.35 | N13: =IF(M13="","",IF(M13>=Assumptions!$B$14,"Tier 1",IF(M13>=Assumptions!$B$15,"Tier 2",IF(M13>=Assumptions!$B$16,"Tier 3","Tier 4")))) -> Tier 2 | P13: Major consumer goods company with strong sustainability commitments. Sustainable Living Brands program. Sources from farmers but limited direct land control. Source: Unilever Annual Reports, sustainability disclosures.
A14: Tyson Foods | B14: USA | C14: =IFERROR(VLOOKUP(B14,Lists!$A$2:$B$200,2,FALSE()),"North America") -> North America | D14: Vertically integrated protein processor | E14: USA (primarily), some operations in China, India | F14: Poultry, Beef, Pork, Animal feed (corn, soy) | G14: 4 | H14: 2 | I14: 4 | J14: 5 | K14: 4 | L14: -1 | M14: =IFERROR((G14*Assumptions!$B$5 + H14*Assumptions!$B$6 + I14*Assumptions!$B$7 + J14*Assumptions!$B$8 + K14*Assumptions!$B$9 + L14*Assumptions!$B$10),"" ) -> 4 | N14: =IF(M14="","",IF(M14>=Assumptions!$B$14,"Tier 1",IF(M14>=Assumptions!$B$15,"Tier 2",IF(M14>=Assumptions!$B$16,"Tier 3","Tier 4")))) -> Tier 1 | P14: Largest US meat processor. Works with contract growers for poultry. Owns feed mills, processing plants. Focus on animal protein. Source: Tyson Annual Reports, sustainability reports.
A15: George Weston | B15: Canada | C15: =IFERROR(VLOOKUP(B15,Lists!$A$2:$B$200,2,FALSE()),"North America") -> North America | D15: Diversified food & retail holding | E15: Canada, USA (via Loblaw, Weston Foods) | F15: Wheat (bakery), Fresh produce (retail) | G15: 1 | H15: 2 | I15: 4 | J15: 3 | K15: 3 | L15: -1 | M15: =IFERROR((G15*Assumptions!$B$5 + H15*Assumptions!$B$6 + I15*Assumptions!$B$7 + J15*Assumptions!$B$8 + K15*Assumptions!$B$9 + L15*Assumptions!$B$10),"" ) -> 2.3 | N15: =IF(M15="","",IF(M15>=Assumptions!$B$14,"Tier 1",IF(M15>=Assumptions!$B$15,"Tier 2",IF(M15>=Assumptions!$B$16,"Tier 3","Tier 4")))) -> Tier 4 | P15: Canadian holding company - Loblaw (retail), Weston Foods (bakery). No significant direct farming. Bakery operations use commodity wheat. Source: George Weston Annual Reports.
A16: Wilmar International | B16: Singapore | C16: =IFERROR(VLOOKUP(B16,Lists!$A$2:$B$200,2,FALSE()),"Asia") -> Asia | D16: Integrated agribusiness | E16: Indonesia, Malaysia, Africa, China, India (palm, sugar, oilseeds) | F16: Palm oil, Sugar cane, Soybeans, Rice, Edible oils | G16: 5 | H16: 2 | I16: 2 | J16: 5 | K16: 4 | L16: -1 | M16: =IFERROR((G16*Assumptions!$B$5 + H16*Assumptions!$B$6 + I16*Assumptions!$B$7 + J16*Assumptions!$B$8 + K16*Assumptions!$B$9 + L16*Assumptions!$B$10),"" ) -> 4.15 | N16: =IF(M16="","",IF(M16>=Assumptions!$B$14,"Tier 1",IF(M16>=Assumptions!$B$15,"Tier 2",IF(M16>=Assumptions!$B$16,"Tier 3","Tier 4")))) -> Tier 1 | P16: Asia's leading agribusiness. Owns/operates ~230,000 ha of oil palm plantations + sugar estates. Highly integrated from plantation to consumer products. Strong in SE Asia. Source: Wilmar Annual Reports.
A17: Compass Group | B17: UK | C17: =IFERROR(VLOOKUP(B17,Lists!$A$2:$B$200,2,FALSE()),"Europe") -> Europe | D17: Contract foodservice | E17: Global (45+ countries, no direct farming) | F17: All categories (sourced from suppliers) | G17: 0 | H17: 3 | I17: 3 | J17: 1 | K17: 3 | L17: 0 | M17: =IFERROR((G17*Assumptions!$B$5 + H17*Assumptions!$B$6 + I17*Assumptions!$B$7 + J17*Assumptions!$B$8 + K17*Assumptions!$B$9 + L17*Assumptions!$B$10),"" ) -> 1.35 | N17: =IF(M17="","",IF(M17>=Assumptions!$B$14,"Tier 1",IF(M17>=Assumptions!$B$15,"Tier 2",IF(M17>=Assumptions!$B$16,"Tier 3","Tier 4")))) -> Tier 4 | P17: World's largest contract foodservice company. No direct farming - influences suppliers through procurement specs. Could drive supplier adoption through requirements. Source: Compass Group Annual Reports.
A18: US Foods | B18: USA | C18: =IFERROR(VLOOKUP(B18,Lists!$A$2:$B$200,2,FALSE()),"North America") -> North America | D18: Foodservice distribution | E18: USA (no direct farm control) | F18: All categories (sourced from suppliers) | G18: 0 | H18: 3 | I18: 4 | J18: 1 | K18: 2 | L18: 0 | M18: =IFERROR((G18*Assumptions!$B$5 + H18*Assumptions!$B$6 + I18*Assumptions!$B$7 + J18*Assumptions!$B$8 + K18*Assumptions!$B$9 + L18*Assumptions!$B$10),"" ) -> 1.4 | N18: =IF(M18="","",IF(M18>=Assumptions!$B$14,"Tier 1",IF(M18>=Assumptions!$B$15,"Tier 2",IF(M18>=Assumptions!$B$16,"Tier 3","Tier 4")))) -> Tier 4 | P18: Second-largest foodservice distributor in US. No direct farming operations. Source: US Foods Annual Reports.
A19: Mondelez International | B19: USA | C19: =IFERROR(VLOOKUP(B19,Lists!$A$2:$B$200,2,FALSE()),"North America") -> North America | D19: Global snack food manufacturer | E19: Côte d'Ivoire, Ghana, India (cocoa programs) | F19: Cocoa, Wheat, Sugar, Dairy, Nuts | G19: 2 | H19: 4 | I19: 4 | J19: 4 | K19: 5 | L19: -1 | M19: =IFERROR((G19*Assumptions!$B$5 + H19*Assumptions!$B$6 + I19*Assumptions!$B$7 + J19*Assumptions!$B$8 + K19*Assumptions!$B$9 + L19*Assumptions!$B$10),"" ) -> 3.45 | N19: =IF(M19="","",IF(M19>=Assumptions!$B$14,"Tier 1",IF(M19>=Assumptions!$B$15,"Tier 2",IF(M19>=Assumptions!$B$16,"Tier 3","Tier 4")))) -> Tier 2 | P19: Global snack leader (Oreo, Cadbury, Toblerone). Cocoa Life program works with farmers but limited direct farming. Focus on processed snacks. Source: Mondelez Annual Reports.
A20: Marfrig Global Foods | B20: Brazil | C20: =IFERROR(VLOOKUP(B20,Lists!$A$2:$B$200,2,FALSE()),"Latin America") -> Latin America | D20: Integrated beef processor | E20: Brazil, Argentina, Uruguay, USA (cattle operations) | F20: Beef, Animal feed (pasture, corn) | G20: 4 | H20: 2 | I20: 3 | J20: 4 | K20: 3 | L20: -1 | M20: =IFERROR((G20*Assumptions!$B$5 + H20*Assumptions!$B$6 + I20*Assumptions!$B$7 + J20*Assumptions!$B$8 + K20*Assumptions!$B$9 + L20*Assumptions!$B$10),"" ) -> 3.55 | N20: =IF(M20="","",IF(M20>=Assumptions!$B$14,"Tier 1",IF(M20>=Assumptions!$B$15,"Tier 2",IF(M20>=Assumptions!$B$16,"Tier 3","Tier 4")))) -> Tier 2 | P20: Second-largest beef producer globally. Owns feedlots and processing in South America. Controls significant beef production chain. Source: Marfrig Annual Reports.
A21: WH Group | B21: Hong Kong | C21: =IFERROR(VLOOKUP(B21,Lists!$A$2:$B$200,2,FALSE()),"Asia") -> Asia | D21: Integrated pork processor | E21: China, USA (Smithfield), Europe | F21: Pork, Animal feed (corn, soybeans) | G21: 5 | H21: 2 | I21: 2 | J21: 5 | K21: 4 | L21: -2 | M21: =IFERROR((G21*Assumptions!$B$5 + H21*Assumptions!$B$6 + I21*Assumptions!$B$7 + J21*Assumptions!$B$8 + K21*Assumptions!$B$9 + L21*Assumptions!$B$10),"" ) -> 4.25 | N21: =IF(M21="","",IF(M21>=Assumptions!$B$14,"Tier 1",IF(M21>=Assumptions!$B$15,"Tier 2",IF(M21>=Assumptions!$B$16,"Tier 3","Tier 4")))) -> Tier 1 | P21: World's largest pork company. Owns Smithfield Foods (USA). Fully integrated from breeding to processing. Controls hog farms, feed mills, processing plants. Source: WH Group Annual Reports.
A22: Associated British Foods | B22: UK | C22: =IFERROR(VLOOKUP(B22,Lists!$A$2:$B$200,2,FALSE()),"Europe") -> Europe | D22: Diversified food & retail | E22: UK, Spain, China, Australia (sugar, ingredients) | F22: Sugar (beet/cane), Wheat, Yeast ingredients | G22: 4 | H22: 2 | I22: 3 | J22: 4 | K22: 3 | L22: -1 | M22: =IFERROR((G22*Assumptions!$B$5 + H22*Assumptions!$B$6 + I22*Assumptions!$B$7 + J22*Assumptions!$B$8 + K22*Assumptions!$B$9 + L22*Assumptions!$B$10),"" ) -> 3.55 | N22: =IF(M22="","",IF(M22>=Assumptions!$B$14,"Tier 1",IF(M22>=Assumptions!$B$15,"Tier 2",IF(M22>=Assumptions!$B$16,"Tier 3","Tier 4")))) -> Tier 2 | P22: Diversified company - AB Sugar (significant beet/cane estates via Illovo in Africa), AB Agri, Primark retail. Strong sugar estate ownership especially in Southern Africa. Source: ABF Annual Reports.
A23: McDonald | B23: USA | C23: =IFERROR(VLOOKUP(B23,Lists!$A$2:$B$200,2,FALSE()),"North America") -> North America | D23: Quick service restaurant | E23: Global (100+ countries, no direct farming) | F23: Potatoes, Beef, Lettuce, Tomatoes (sourced) | G23: 0 | H23: 3 | I23: 4 | J23: 1 | K23: 5 | L23: 0 | M23: =IFERROR((G23*Assumptions!$B$5 + H23*Assumptions!$B$6 + I23*Assumptions!$B$7 + J23*Assumptions!$B$8 + K23*Assumptions!$B$9 + L23*Assumptions!$B$10),"" ) -> 1.55 | N23: =IF(M23="","",IF(M23>=Assumptions!$B$14,"Tier 1",IF(M23>=Assumptions!$B$15,"Tier 2",IF(M23>=Assumptions!$B$16,"Tier 3","Tier 4")))) -> Tier 4 | P23: World's largest restaurant company. No direct farming but strong supplier requirements. Sustainability programs (Flagship Farms) influence suppliers. Could drive adoption through supplier mandates. Source: McDonald's Annual Reports.
A24: Kraft Heinz | B24: USA | C24: =IFERROR(VLOOKUP(B24,Lists!$A$2:$B$200,2,FALSE()),"North America") -> North America | D24: Food & beverage manufacturer | E24: USA, Canada, UK, EU (tomato processing) | F24: Tomatoes, Potatoes, Vegetables, Dairy, Wheat | G24: 2 | H24: 3 | I24: 4 | J24: 3 | K24: 4 | L24: -1 | M24: =IFERROR((G24*Assumptions!$B$5 + H24*Assumptions!$B$6 + I24*Assumptions!$B$7 + J24*Assumptions!$B$8 + K24*Assumptions!$B$9 + L24*Assumptions!$B$10),"" ) -> 2.9 | N24: =IF(M24="","",IF(M24>=Assumptions!$B$14,"Tier 1",IF(M24>=Assumptions!$B$15,"Tier 2",IF(M24>=Assumptions!$B$16,"Tier 3","Tier 4")))) -> Tier 3 | P24: Major food company (Heinz, Kraft, Oscar Mayer). Heinz tomato operations involve some contract growing. Limited direct land ownership. Source: Kraft Heinz Annual Reports.
A25: Olam | B25: Singapore | C25: =IFERROR(VLOOKUP(B25,Lists!$A$2:$B$200,2,FALSE()),"Asia") -> Asia | D25: Integrated agribusiness | E25: Africa, Asia, Australia, Americas (extensive farm ownership) | F25: Cocoa, Coffee, Nuts, Spices, Cotton, Rice, Rubber | G25: 5 | H25: 4 | I25: 2 | J25: 5 | K25: 4 | L25: -1 | M25: =IFERROR((G25*Assumptions!$B$5 + H25*Assumptions!$B$6 + I25*Assumptions!$B$7 + J25*Assumptions!$B$8 + K25*Assumptions!$B$9 + L25*Assumptions!$B$10),"" ) -> 4.55 | N25: =IF(M25="","",IF(M25>=Assumptions!$B$14,"Tier 1",IF(M25>=Assumptions!$B$15,"Tier 2",IF(M25>=Assumptions!$B$16,"Tier 3","Tier 4")))) -> Tier 1 | P25: Major integrated agribusiness. Owns ~700,000+ ha farmland (almond orchards, coffee estates, cocoa farms, palm plantations). Highly integrated from farm to customer. Strong position in specialty crops. Source: Olam Annual Reports.
A26: Empire Company | B26: Canada | C26: =IFERROR(VLOOKUP(B26,Lists!$A$2:$B$200,2,FALSE()),"North America") -> North America | D26: Retail/supermarket chain | E26: Canada (via Sobeys, no direct farming) | F26: Fresh produce (sourced from suppliers) | G26: 0 | H26: 3 | I26: 4 | J26: 1 | K26: 2 | L26: 0 | M26: =IFERROR((G26*Assumptions!$B$5 + H26*Assumptions!$B$6 + I26*Assumptions!$B$7 + J26*Assumptions!$B$8 + K26*Assumptions!$B$9 + L26*Assumptions!$B$10),"" ) -> 1.4 | N26: =IF(M26="","",IF(M26>=Assumptions!$B$14,"Tier 1",IF(M26>=Assumptions!$B$15,"Tier 2",IF(M26>=Assumptions!$B$16,"Tier 3","Tier 4")))) -> Tier 4 | P26: Canadian retailer (Sobeys, Safeway Canada, IGA). No direct farming operations. Source: Empire Company Annual Reports.
A27: Muyuan Foods | B27: China | C27: =IFERROR(VLOOKUP(B27,Lists!$A$2:$B$200,2,FALSE()),"Asia") -> Asia | D27: Integrated hog producer | E27: China (extensive hog operations) | F27: Pork, Animal feed (corn, soy) | G27: 5 | H27: 2 | I27: 1 | J27: 5 | K27: 3 | L27: -2 | M27: =IFERROR((G27*Assumptions!$B$5 + H27*Assumptions!$B$6 + I27*Assumptions!$B$7 + J27*Assumptions!$B$8 + K27*Assumptions!$B$9 + L27*Assumptions!$B$10),"" ) -> 4.1 | N27: =IF(M27="","",IF(M27>=Assumptions!$B$14,"Tier 1",IF(M27>=Assumptions!$B$15,"Tier 2",IF(M27>=Assumptions!$B$16,"Tier 3","Tier 4")))) -> Tier 1 | P27: China's largest hog breeding company. Fully integrated operations - breeding, growing, processing. Focus on swine, limited biostimulant relevance for crops. Source: Muyuan Foods Annual Reports.
A28: Grupo Bimbo | B28: Mexico | C28: =IFERROR(VLOOKUP(B28,Lists!$A$2:$B$200,2,FALSE()),"Latin America") -> Latin America | D28: Global bakery company | E28: Mexico, USA, Latin America, Europe (limited farming) | F28: Wheat, Sugar, Oils (sourced) | G28: 1 | H28: 2 | I28: 3 | J28: 3 | K28: 4 | L28: -1 | M28: =IFERROR((G28*Assumptions!$B$5 + H28*Assumptions!$B$6 + I28*Assumptions!$B$7 + J28*Assumptions!$B$8 + K28*Assumptions!$B$9 + L28*Assumptions!$B$10),"" ) -> 2.25 | N28: =IF(M28="","",IF(M28>=Assumptions!$B$14,"Tier 1",IF(M28>=Assumptions!$B$15,"Tier 2",IF(M28>=Assumptions!$B$16,"Tier 3","Tier 4")))) -> Tier 4 | P28: World's largest bakery company. Owns processing but sources wheat/ingredients. Limited direct farming involvement. Source: Grupo Bimbo Annual Reports.
A29: Uni-President Enterprises | B29: Taiwan | C29: =IFERROR(VLOOKUP(B29,Lists!$A$2:$B$200,2,FALSE()),"Asia") -> Asia | D29: Diversified food conglomerate | E29: Taiwan, China, SE Asia | F29: Flour/Wheat, Beverages, Animal feed | G29: 2 | H29: 2 | I29: 2 | J29: 3 | K29: 3 | L29: -1 | M29: =IFERROR((G29*Assumptions!$B$5 + H29*Assumptions!$B$6 + I29*Assumptions!$B$7 + J29*Assumptions!$B$8 + K29*Assumptions!$B$9 + L29*Assumptions!$B$10),"" ) -> 2.45 | N29: =IF(M29="","",IF(M29>=Assumptions!$B$14,"Tier 1",IF(M29>=Assumptions!$B$15,"Tier 2",IF(M29>=Assumptions!$B$16,"Tier 3","Tier 4")))) -> Tier 4 | P29: Taiwanese food conglomerate. Operates instant noodles, beverages, retail (7-Eleven Asia). Some flour milling, feed operations. Source: Uni-President Annual Reports.
A30: General Mills | B30: USA | C30: =IFERROR(VLOOKUP(B30,Lists!$A$2:$B$200,2,FALSE()),"North America") -> North America | D30: Food manufacturer | E30: USA, Canada, EU (limited direct farming) | F30: Wheat, Oats, Corn, Sugar, Dairy | G30: 1 | H30: 2 | I30: 4 | J30: 3 | K30: 4 | L30: -1 | M30: =IFERROR((G30*Assumptions!$B$5 + H30*Assumptions!$B$6 + I30*Assumptions!$B$7 + J30*Assumptions!$B$8 + K30*Assumptions!$B$9 + L30*Assumptions!$B$10),"" ) -> 2.35 | N30: =IF(M30="","",IF(M30>=Assumptions!$B$14,"Tier 1",IF(M30>=Assumptions!$B$15,"Tier 2",IF(M30>=Assumptions!$B$16,"Tier 3","Tier 4")))) -> Tier 4 | P30: Major US food company (Cheerios, Häagen-Dazs, Blue Buffalo). Sources ingredients from farmers. Sustainability commitments but limited direct farming. Source: General Mills Annual Reports.
A31: Aramark | B31: USA | C31: =IFERROR(VLOOKUP(B31,Lists!$A$2:$B$200,2,FALSE()),"North America") -> North America | D31: Contract foodservice | E31: USA, Europe, Asia (no direct farming) | F31: All categories (sourced from suppliers) | G31: 0 | H31: 3 | I31: 4 | J31: 1 | K31: 3 | L31: 0 | M31: =IFERROR((G31*Assumptions!$B$5 + H31*Assumptions!$B$6 + I31*Assumptions!$B$7 + J31*Assumptions!$B$8 + K31*Assumptions!$B$9 + L31*Assumptions!$B$10),"" ) -> 1.45 | N31: =IF(M31="","",IF(M31>=Assumptions!$B$14,"Tier 1",IF(M31>=Assumptions!$B$15,"Tier 2",IF(M31>=Assumptions!$B$16,"Tier 3","Tier 4")))) -> Tier 4 | P31: Major contract foodservice company. No direct farming operations. Could influence suppliers through procurement standards. Source: Aramark Annual Reports.
A32: Pilgrim's Pride | B32: USA | C32: =IFERROR(VLOOKUP(B32,Lists!$A$2:$B$200,2,FALSE()),"North America") -> North America | D32: Integrated poultry processor | E32: USA, Mexico, UK (poultry operations) | F32: Poultry, Animal feed (corn, soy) | G32: 4 | H32: 2 | I32: 4 | J32: 4 | K32: 3 | L32: -1 | M32: =IFERROR((G32*Assumptions!$B$5 + H32*Assumptions!$B$6 + I32*Assumptions!$B$7 + J32*Assumptions!$B$8 + K32*Assumptions!$B$9 + L32*Assumptions!$B$10),"" ) -> 3.65 | N32: =IF(M32="","",IF(M32>=Assumptions!$B$14,"Tier 1",IF(M32>=Assumptions!$B$15,"Tier 2",IF(M32>=Assumptions!$B$16,"Tier 3","Tier 4")))) -> Tier 2 | P32: Major US poultry producer (subsidiary of JBS). Contract grower model for chickens. Owns feed mills, hatcheries, processing plants. Source: Pilgrim's Pride Annual Reports.
A33: Charoen Pokphand Foods | B33: Thailand | C33: =IFERROR(VLOOKUP(B33,Lists!$A$2:$B$200,2,FALSE()),"Asia") -> Asia | D33: Integrated agro-industrial conglomerate | E33: Thailand, Vietnam, China, India, Turkey (extensive) | F33: Shrimp, Poultry, Swine, Animal feed | G33: 5 | H33: 3 | I33: 2 | J33: 5 | K33: 4 | L33: -2 | M33: =IFERROR((G33*Assumptions!$B$5 + H33*Assumptions!$B$6 + I33*Assumptions!$B$7 + J33*Assumptions!$B$8 + K33*Assumptions!$B$9 + L33*Assumptions!$B$10),"" ) -> 4.45 | N33: =IF(M33="","",IF(M33>=Assumptions!$B$14,"Tier 1",IF(M33>=Assumptions!$B$15,"Tier 2",IF(M33>=Assumptions!$B$16,"Tier 3","Tier 4")))) -> Tier 1 | P33: Thailand's largest agribusiness. Fully integrated - feed mills, farms (shrimp, poultry, swine), processing, retail. Strong in aquaculture and livestock. Source: CP Foods Annual Reports.
A34: Sodexo | B34: France | C34: =IFERROR(VLOOKUP(B34,Lists!$A$2:$B$200,2,FALSE()),"Europe") -> Europe | D34: Contract foodservice | E34: Global (56 countries, no direct farming) | F34: All categories (sourced from suppliers) | G34: 0 | H34: 3 | I34: 3 | J34: 1 | K34: 3 | L34: 0 | M34: =IFERROR((G34*Assumptions!$B$5 + H34*Assumptions!$B$6 + I34*Assumptions!$B$7 + J34*Assumptions!$B$8 + K34*Assumptions!$B$9 + L34*Assumptions!$B$10),"" ) -> 1.35 | N34: =IF(M34="","",IF(M34>=Assumptions!$B$14,"Tier 1",IF(M34>=Assumptions!$B$15,"Tier 2",IF(M34>=Assumptions!$B$16,"Tier 3","Tier 4")))) -> Tier 4 | P34: Second-largest contract foodservice company. No direct farming. Influences suppliers through procurement. Source: Sodexo Annual Reports.
A35: Guangdong HAID Group | B35: China | C35: =IFERROR(VLOOKUP(B35,Lists!$A$2:$B$200,2,FALSE()),"Asia") -> Asia | D35: Animal feed producer | E35: China, SE Asia (feed operations) | F35: Animal feed (corn, soy, fishmeal) | G35: 3 | H35: 2 | I35: 1 | J35: 4 | K35: 3 | L35: -2 | M35: =IFERROR((G35*Assumptions!$B$5 + H35*Assumptions!$B$6 + I35*Assumptions!$B$7 + J35*Assumptions!$B$8 + K35*Assumptions!$B$9 + L35*Assumptions!$B$10),"" ) -> 3.1 | N35: =IF(M35="","",IF(M35>=Assumptions!$B$14,"Tier 1",IF(M35>=Assumptions!$B$15,"Tier 2",IF(M35>=Assumptions!$B$16,"Tier 3","Tier 4")))) -> Tier 3 | P35: Major Chinese aquafeed and animal feed company. Focus on feed production. Some integration into farming but primarily B2B feed supplier. Source: HAID Group Annual Reports.
A36: Danone | B36: France | C36: =IFERROR(VLOOKUP(B36,Lists!$A$2:$B$200,2,FALSE()),"Europe") -> Europe | D36: Dairy & specialty food manufacturer | E36: France, USA, China (dairy sourcing programs) | F36: Dairy, Water, Plant-based ingredients | G36: 2 | H36: 3 | I36: 4 | J36: 3 | K36: 4 | L36: -1 | M36: =IFERROR((G36*Assumptions!$B$5 + H36*Assumptions!$B$6 + I36*Assumptions!$B$7 + J36*Assumptions!$B$8 + K36*Assumptions!$B$9 + L36*Assumptions!$B$10),"" ) -> 2.9 | N36: =IF(M36="","",IF(M36>=Assumptions!$B$14,"Tier 1",IF(M36>=Assumptions!$B$15,"Tier 2",IF(M36>=Assumptions!$B$16,"Tier 3","Tier 4")))) -> Tier 3 | P36: Global dairy leader. Works with dairy farmers through programs but limited direct land ownership. Strong sustainability focus (B Corp). Source: Danone Annual Reports.
A37: Smithfield Foods | B37: USA | C37: =IFERROR(VLOOKUP(B37,Lists!$A$2:$B$200,2,FALSE()),"North America") -> North America | D37: Integrated pork processor | E37: USA, Poland, Romania, Mexico (pork operations) | F37: Pork, Animal feed (corn, soy) | G37: 5 | H37: 2 | I37: 4 | J37: 5 | K37: 4 | L37: -1 | M37: =IFERROR((G37*Assumptions!$B$5 + H37*Assumptions!$B$6 + I37*Assumptions!$B$7 + J37*Assumptions!$B$8 + K37*Assumptions!$B$9 + L37*Assumptions!$B$10),"" ) -> 4.35 | N37: =IF(M37="","",IF(M37>=Assumptions!$B$14,"Tier 1",IF(M37>=Assumptions!$B$15,"Tier 2",IF(M37>=Assumptions!$B$16,"Tier 3","Tier 4")))) -> Tier 1 | P37: Largest US pork producer (owned by WH Group). Fully integrated - hog farms, feed mills, processing. Controls significant production chain. Source: Smithfield Foods website, WH Group reports.
A38: Kirin Holdings | B38: Japan | C38: =IFERROR(VLOOKUP(B38,Lists!$A$2:$B$200,2,FALSE()),"Asia") -> Asia | D38: Beverage & pharmaceutical conglomerate | E38: Japan, Australia, SE Asia | F38: Barley, Hops, Tea (sourced) | G38: 1 | H38: 2 | I38: 3 | J38: 2 | K38: 3 | L38: -1 | M38: =IFERROR((G38*Assumptions!$B$5 + H38*Assumptions!$B$6 + I38*Assumptions!$B$7 + J38*Assumptions!$B$8 + K38*Assumptions!$B$9 + L38*Assumptions!$B$10),"" ) -> 1.9 | N38: =IF(M38="","",IF(M38>=Assumptions!$B$14,"Tier 1",IF(M38>=Assumptions!$B$15,"Tier 2",IF(M38>=Assumptions!$B$16,"Tier 3","Tier 4")))) -> Tier 4 | P38: Japanese beverage conglomerate (beer, soft drinks). Sources barley, hops for brewing. Limited direct farming. Source: Kirin Holdings Annual Reports.
A39: Fonterra | B39: New Zealand | C39: =IFERROR(VLOOKUP(B39,Lists!$A$2:$B$200,2,FALSE()),"Oceania") -> Oceania | D39: Dairy cooperative | E39: New Zealand, Australia (dairy farms) | F39: Dairy (pasture-based), Grass/fodder | G39: 4 | H39: 3 | I39: 5 | J39: 4 | K39: 4 | L39: 0 | M39: =IFERROR((G39*Assumptions!$B$5 + H39*Assumptions!$B$6 + I39*Assumptions!$B$7 + J39*Assumptions!$B$8 + K39*Assumptions!$B$9 + L39*Assumptions!$B$10),"" ) -> 3.9 | N39: =IF(M39="","",IF(M39>=Assumptions!$B$14,"Tier 1",IF(M39>=Assumptions!$B$15,"Tier 2",IF(M39>=Assumptions!$B$16,"Tier 3","Tier 4")))) -> Tier 2 | P39: New Zealand dairy cooperative - collective of ~10,000 dairy farmers. Strong influence over farm practices through cooperative structure. Focus on pasture management. Source: Fonterra Annual Reports.
A40: Saputo | B40: Canada | C40: =IFERROR(VLOOKUP(B40,Lists!$A$2:$B$200,2,FALSE()),"North America") -> North America | D40: Dairy processor | E40: Canada, USA, Australia, Argentina (dairy sourcing) | F40: Dairy (sourced from farms) | G40: 1 | H40: 3 | I40: 4 | J40: 3 | K40: 3 | L40: 0 | M40: =IFERROR((G40*Assumptions!$B$5 + H40*Assumptions!$B$6 + I40*Assumptions!$B$7 + J40*Assumptions!$B$8 + K40*Assumptions!$B$9 + L40*Assumptions!$B$10),"" ) -> 2.4 | N40: =IF(M40="","",IF(M40>=Assumptions!$B$14,"Tier 1",IF(M40>=Assumptions!$B$15,"Tier 2",IF(M40>=Assumptions!$B$16,"Tier 3","Tier 4")))) -> Tier 4 | P40: Major dairy processor. Sources milk from dairy farmers - limited direct farm control. Focus on cheese, fluid milk processing. Source: Saputo Annual Reports.
A41: DSM-Firmenich | B41: Switzerland | C41: =IFERROR(VLOOKUP(B41,Lists!$A$2:$B$200,2,FALSE()),"Europe") -> Europe | D41: Nutrition & ingredients company | E41: Global (no significant direct farming) | F41: Vitamins, Flavors, Enzymes (manufactured/sourced) | G41: 1 | H41: 5 | I41: 4 | J41: 2 | K41: 4 | L41: -1 | M41: =IFERROR((G41*Assumptions!$B$5 + H41*Assumptions!$B$6 + I41*Assumptions!$B$7 + J41*Assumptions!$B$8 + K41*Assumptions!$B$9 + L41*Assumptions!$B$10),"" ) -> 2.65 | N41: =IF(M41="","",IF(M41>=Assumptions!$B$14,"Tier 1",IF(M41>=Assumptions!$B$15,"Tier 2",IF(M41>=Assumptions!$B$16,"Tier 3","Tier 4")))) -> Tier 3 | P41: Global nutrition and ingredients company (merged DSM + Firmenich). Manufactures vitamins, flavors, enzymes. Limited direct farming but could be partner for ingredient synergies. Source: DSM-Firmenich reports.
A42: Kellanova (Kellogg's) | B42: USA | C42: =IFERROR(VLOOKUP(B42,Lists!$A$2:$B$200,2,FALSE()),"North America") -> North America | D42: Cereal & snack manufacturer | E42: USA, Europe, LATAM (sourcing programs) | F42: Corn, Wheat, Rice, Oats, Potatoes | G42: 2 | H42: 2 | I42: 4 | J42: 3 | K42: 4 | L42: -1 | M42: =IFERROR((G42*Assumptions!$B$5 + H42*Assumptions!$B$6 + I42*Assumptions!$B$7 + J42*Assumptions!$B$8 + K42*Assumptions!$B$9 + L42*Assumptions!$B$10),"" ) -> 2.7 | N42: =IF(M42="","",IF(M42>=Assumptions!$B$14,"Tier 1",IF(M42>=Assumptions!$B$15,"Tier 2",IF(M42>=Assumptions!$B$16,"Tier 3","Tier 4")))) -> Tier 3 | P42: Snack company spun from Kellogg's (2023). Responsible sourcing programs with farmers but limited direct ownership. Focus on commodity grains for snacks. Source: Kellanova Annual Reports.
A43: DoorDash | B43: USA | C43: =IFERROR(VLOOKUP(B43,Lists!$A$2:$B$200,2,FALSE()),"North America") -> North America | D43: Food delivery platform | E43: USA, Canada, Australia, Japan (no farming) | F43: N/A (delivery platform) | G43: 0 | H43: 0 | I43: 4 | J43: 0 | K43: 2 | L43: 0 | M43: =IFERROR((G43*Assumptions!$B$5 + H43*Assumptions!$B$6 + I43*Assumptions!$B$7 + J43*Assumptions!$B$8 + K43*Assumptions!$B$9 + L43*Assumptions!$B$10),"" ) -> 0.5 | N43: =IF(M43="","",IF(M43>=Assumptions!$B$14,"Tier 1",IF(M43>=Assumptions!$B$15,"Tier 2",IF(M43>=Assumptions!$B$16,"Tier 3","Tier 4")))) -> Tier 4 | P43: Food delivery platform. No direct involvement in food production or farming. Not relevant for biostimulant partnerships. Source: DoorDash Annual Reports.
A44: Darden Restaurants | B44: USA | C44: =IFERROR(VLOOKUP(B44,Lists!$A$2:$B$200,2,FALSE()),"North America") -> North America | D44: Casual dining restaurant company | E44: USA, Canada (no direct farming) | F44: Seafood, Produce (sourced) | G44: 0 | H44: 3 | I44: 4 | J44: 1 | K44: 3 | L44: 0 | M44: =IFERROR((G44*Assumptions!$B$5 + H44*Assumptions!$B$6 + I44*Assumptions!$B$7 + J44*Assumptions!$B$8 + K44*Assumptions!$B$9 + L44*Assumptions!$B$10),"" ) -> 1.45 | N44: =IF(M44="","",IF(M44>=Assumptions!$B$14,"Tier 1",IF(M44>=Assumptions!$B$15,"Tier 2",IF(M44>=Assumptions!$B$16,"Tier 3","Tier 4")))) -> Tier 4 | P44: US restaurant company (Olive Garden, LongHorn Steakhouse). No direct farming - sources from suppliers. Source: Darden Annual Reports.
A45: Bid Corp | B45: South Africa | C45: =IFERROR(VLOOKUP(B45,Lists!$A$2:$B$200,2,FALSE()),"Africa") -> Africa | D45: Foodservice distribution | E45: South Africa, UK, Australasia, Europe | F45: All categories (sourced from suppliers) | G45: 0 | H45: 3 | I45: 3 | J45: 1 | K45: 3 | L45: 0 | M45: =IFERROR((G45*Assumptions!$B$5 + H45*Assumptions!$B$6 + I45*Assumptions!$B$7 + J45*Assumptions!$B$8 + K45*Assumptions!$B$9 + L45*Assumptions!$B$10),"" ) -> 1.35 | N45: =IF(M45="","",IF(M45>=Assumptions!$B$14,"Tier 1",IF(M45>=Assumptions!$B$15,"Tier 2",IF(M45>=Assumptions!$B$16,"Tier 3","Tier 4")))) -> Tier 4 | P45: Global foodservice distributor (spun from Bid Corporation). Strong in South Africa, UK, Australasia. No direct farming. Source: Bidcorp Annual Reports.
A46: Barry Callebaut | B46: Switzerland | C46: =IFERROR(VLOOKUP(B46,Lists!$A$2:$B$200,2,FALSE()),"Europe") -> Europe | D46: Cocoa & chocolate manufacturer | E46: Côte d'Ivoire, Ghana, Indonesia, Brazil (cocoa sourcing) | F46: Cocoa, Chocolate | G46: 3 | H46: 5 | I46: 3 | J46: 4 | K46: 5 | L46: -1 | M46: =IFERROR((G46*Assumptions!$B$5 + H46*Assumptions!$B$6 + I46*Assumptions!$B$7 + J46*Assumptions!$B$8 + K46*Assumptions!$B$9 + L46*Assumptions!$B$10),"" ) -> 3.9 | N46: =IF(M46="","",IF(M46>=Assumptions!$B$14,"Tier 1",IF(M46>=Assumptions!$B$15,"Tier 2",IF(M46>=Assumptions!$B$16,"Tier 3","Tier 4")))) -> Tier 2 | P46: [WATCH LIST] World's largest cocoa processor and chocolate manufacturer (B2B). Forever Chocolate program involves direct farmer relationships. Strong influence over cocoa farming practices. Source: Barry Callebaut Annual Reports.
A47: Mengniu Dairy | B47: China | C47: =IFERROR(VLOOKUP(B47,Lists!$A$2:$B$200,2,FALSE()),"Asia") -> Asia | D47: Dairy company | E47: China, Australia, New Zealand | F47: Dairy, Pasture | G47: 3 | H47: 3 | I47: 1 | J47: 4 | K47: 3 | L47: -2 | M47: =IFERROR((G47*Assumptions!$B$5 + H47*Assumptions!$B$6 + I47*Assumptions!$B$7 + J47*Assumptions!$B$8 + K47*Assumptions!$B$9 + L47*Assumptions!$B$10),"" ) -> 3.3 | N47: =IF(M47="","",IF(M47>=Assumptions!$B$14,"Tier 1",IF(M47>=Assumptions!$B$15,"Tier 2",IF(M47>=Assumptions!$B$16,"Tier 3","Tier 4")))) -> Tier 2 | P47: China's largest dairy company. Owns some dairy farms and works with farmer suppliers. Focus on fluid milk, yogurt, ice cream. Source: Mengniu Annual Reports.
A48: Hormel Foods | B48: USA | C48: =IFERROR(VLOOKUP(B48,Lists!$A$2:$B$200,2,FALSE()),"North America") -> North America | D48: Food manufacturer/processor | E48: USA (primarily), limited international | F48: Pork, Turkey, Nuts, Vegetables | G48: 3 | H48: 3 | I48: 4 | J48: 3 | K48: 3 | L48: 0 | M48: =IFERROR((G48*Assumptions!$B$5 + H48*Assumptions!$B$6 + I48*Assumptions!$B$7 + J48*Assumptions!$B$8 + K48*Assumptions!$B$9 + L48*Assumptions!$B$10),"" ) -> 3.1 | N48: =IF(M48="","",IF(M48>=Assumptions!$B$14,"Tier 1",IF(M48>=Assumptions!$B$15,"Tier 2",IF(M48>=Assumptions!$B$16,"Tier 3","Tier 4")))) -> Tier 3 | P48: [REMOVED] US food company (SPAM, Jennie-O turkey, Planters nuts, Skippy). Integrated turkey operations (Jennie-O). Some direct agricultural involvement. Source: Hormel Foods Annual Reports.
A49: Chipotle Mexican Grill | B49: USA | C49: =IFERROR(VLOOKUP(B49,Lists!$A$2:$B$200,2,FALSE()),"North America") -> North America | D49: Fast-casual restaurant | E49: USA, Canada, UK, Europe (no direct farming) | F49: Avocados, Peppers, Tomatoes, Beef, Rice (sourced) | G49: 1 | H49: 4 | I49: 4 | J49: 2 | K49: 4 | L49: 0 | M49: =IFERROR((G49*Assumptions!$B$5 + H49*Assumptions!$B$6 + I49*Assumptions!$B$7 + J49*Assumptions!$B$8 + K49*Assumptions!$B$9 + L49*Assumptions!$B$10),"" ) -> 2.35 | N49: =IF(M49="","",IF(M49>=Assumptions!$B$14,"Tier 1",IF(M49>=Assumptions!$B$15,"Tier 2",IF(M49>=Assumptions!$B$16,"Tier 3","Tier 4")))) -> Tier 4 | P49: Fast-casual restaurant chain with strong sustainability focus. Responsible sourcing programs, "Food with Integrity". Could influence suppliers but no direct farming. Source: Chipotle Annual Reports.
A50: Yum China | B50: China | C50: =IFERROR(VLOOKUP(B50,Lists!$A$2:$B$200,2,FALSE()),"Asia") -> Asia | D50: Quick service restaurant | E50: China (KFC, Pizza Hut, Taco Bell operations) | F50: Poultry, Vegetables, Wheat (sourced) | G50: 0 | H50: 3 | I50: 1 | J50: 1 | K50: 3 | L50: -2 | M50: =IFERROR((G50*Assumptions!$B$5 + H50*Assumptions!$B$6 + I50*Assumptions!$B$7 + J50*Assumptions!$B$8 + K50*Assumptions!$B$9 + L50*Assumptions!$B$10),"" ) -> 1.35 | N50: =IF(M50="","",IF(M50>=Assumptions!$B$14,"Tier 1",IF(M50>=Assumptions!$B$15,"Tier 2",IF(M50>=Assumptions!$B$16,"Tier 3","Tier 4")))) -> Tier 4 | P50: Largest restaurant company in China (KFC, Pizza Hut). No direct farming - sources from suppliers. Chinese regulatory complexity. Source: Yum China Annual Reports.
A51: The Hershey Company | B51: USA | C51: =IFERROR(VLOOKUP(B51,Lists!$A$2:$B$200,2,FALSE()),"North America") -> North America | D51: Chocolate & confectionery manufacturer | E51: Côte d'Ivoire, Ghana (cocoa sourcing programs) | F51: Cocoa, Sugar, Dairy, Nuts | G51: 2 | H51: 4 | I51: 4 | J51: 3 | K51: 4 | L51: -1 | M51: =IFERROR((G51*Assumptions!$B$5 + H51*Assumptions!$B$6 + I51*Assumptions!$B$7 + J51*Assumptions!$B$8 + K51*Assumptions!$B$9 + L51*Assumptions!$B$10),"" ) -> 3.1 | N51: =IF(M51="","",IF(M51>=Assumptions!$B$14,"Tier 1",IF(M51>=Assumptions!$B$15,"Tier 2",IF(M51>=Assumptions!$B$16,"Tier 3","Tier 4")))) -> Tier 3 | P51: US chocolate company. Cocoa For Good program involves farmer relationships in West Africa. Limited direct land ownership. Source: Hershey Annual Reports.
A52: Conagra Brands | B52: USA | C52: =IFERROR(VLOOKUP(B52,Lists!$A$2:$B$200,2,FALSE()),"North America") -> North America | D52: Packaged food manufacturer | E52: USA (primarily) | F52: Vegetables, Tomatoes, Potatoes, Wheat, Poultry | G52: 2 | H52: 3 | I52: 4 | J52: 3 | K52: 3 | L52: 0 | M52: =IFERROR((G52*Assumptions!$B$5 + H52*Assumptions!$B$6 + I52*Assumptions!$B$7 + J52*Assumptions!$B$8 + K52*Assumptions!$B$9 + L52*Assumptions!$B$10),"" ) -> 2.75 | N52: =IF(M52="","",IF(M52>=Assumptions!$B$14,"Tier 1",IF(M52>=Assumptions!$B$15,"Tier 2",IF(M52>=Assumptions!$B$16,"Tier 3","Tier 4")))) -> Tier 3 | P52: US packaged food company (Birds Eye, Healthy Choice, Duncan Hines, Slim Jim). Some contract growing for vegetables. Source: Conagra Annual Reports.
A53: Campbell's | B53: USA | C53: =IFERROR(VLOOKUP(B53,Lists!$A$2:$B$200,2,FALSE()),"North America") -> North America | D53: Food manufacturer | E53: USA (primarily) | F53: Tomatoes, Vegetables, Wheat, Potatoes | G53: 2 | H53: 3 | I53: 4 | J53: 3 | K53: 3 | L53: 0 | M53: =IFERROR((G53*Assumptions!$B$5 + H53*Assumptions!$B$6 + I53*Assumptions!$B$7 + J53*Assumptions!$B$8 + K53*Assumptions!$B$9 + L53*Assumptions!$B$10),"" ) -> 2.75 | N53: =IF(M53="","",IF(M53>=Assumptions!$B$14,"Tier 1",IF(M53>=Assumptions!$B$15,"Tier 2",IF(M53>=Assumptions!$B$16,"Tier 3","Tier 4")))) -> Tier 3 | P53: US food company (Campbell's Soup, Pepperidge Farm, V8). Contract growing programs for tomatoes and vegetables. Source: Campbell's Annual Reports.
A54: Südzucker | B54: Germany | C54: =IFERROR(VLOOKUP(B54,Lists!$A$2:$B$200,2,FALSE()),"Europe") -> Europe | D54: Sugar & food ingredients producer | E54: Germany, France, Belgium, Poland, UK (sugar beet) | F54: Sugar beet, Bioethanol feedstocks | G54: 4 | H54: 2 | I54: 5 | J54: 4 | K54: 4 | L54: 0 | M54: =IFERROR((G54*Assumptions!$B$5 + H54*Assumptions!$B$6 + I54*Assumptions!$B$7 + J54*Assumptions!$B$8 + K54*Assumptions!$B$9 + L54*Assumptions!$B$10),"" ) -> 3.7 | N54: =IF(M54="","",IF(M54>=Assumptions!$B$14,"Tier 1",IF(M54>=Assumptions!$B$15,"Tier 2",IF(M54>=Assumptions!$B$16,"Tier 3","Tier 4")))) -> Tier 2 | P54: [REMOVED] Europe's largest sugar producer. Works with contracted sugar beet farmers across EU. Strong influence over farming practices. EU biostimulant regulation provides clear pathway. Source: Südzucker Annual Reports.
A55: Ajinomoto | B55: Japan | C55: =IFERROR(VLOOKUP(B55,Lists!$A$2:$B$200,2,FALSE()),"Asia") -> Asia | D55: Food & amino acid manufacturer | E55: Japan, Thailand, Brazil, Vietnam (various operations) | F55: Amino acids, MSG, Seasonings (sugar cane, tapioca) | G55: 3 | H55: 4 | I55: 3 | J55: 3 | K55: 4 | L55: -1 | M55: =IFERROR((G55*Assumptions!$B$5 + H55*Assumptions!$B$6 + I55*Assumptions!$B$7 + J55*Assumptions!$B$8 + K55*Assumptions!$B$9 + L55*Assumptions!$B$10),"" ) -> 3.35 | N55: =IF(M55="","",IF(M55>=Assumptions!$B$14,"Tier 1",IF(M55>=Assumptions!$B$15,"Tier 2",IF(M55>=Assumptions!$B$16,"Tier 3","Tier 4")))) -> Tier 2 | P55: [REMOVED] Japanese company - world leader in amino acids and seasonings. Some integrated agricultural operations for raw materials (sugar cane for fermentation). Source: Ajinomoto Annual Reports.

Sheet Matrix - Top 51-100
A1: Decision Matrix - Target Partners (Top 51-100 food companies globally)
A2: Scores are 0–5. Weighted score and tier update automatically based on Assumptions tab.
A4: Company | B4: HQ Country | C4: Region | D4: Business Type (eg. integrated producer) | E4: Countries with controlled farms | F4: Main crops (top 5) | G4: Integration / Owns Land (0–5) | H4: High-Value Crop Exposure (0–5) | I4: Registration Ease (0–5) | J4: Scale Potential (0–5) | K4: Strategic Leverage (0–5) | L4: Penalty: Complexity (0–-2) | M4: Weighted Score (0–5) | N4: Tier | O4: Owner | P4: Notes / Evidence
A5: Top 51-100 food companies in the world
A6: Lactalis | B6: France | C6: Europe | D6: Dairy processor | E6: France, Italy, USA, Spain (dairy sourcing) | F6: Dairy (milk, cheese, yogurt) | G6: 2 | H6: 3 | I6: 4 | J6: 4 | K6: 4 | L6: -1 | M6: 3.15 | N6: Tier 3 | P6: World's largest dairy company (private). Owns Parmalat, Président, Galbani. Sources from dairy farmers across Europe/US. Limited direct farm ownership. Source: Lactalis company information.
A7: Ferrero | B7: Italy | C7: Other | D7: Confectionery manufacturer | E7: Turkey, Italy, Chile (hazelnut operations) | F7: Hazelnuts, Cocoa, Palm oil, Sugar | G7: 4 | H7: 5 | I7: 4 | J7: 3 | K7: 5 | L7: -1 | M7: 4.25 | N7: Tier 1 | P7: [WATCH LIST]
A8: Perdue Farms | B8: USA | C8: North America | D8: Integrated poultry processor | E8: USA (East Coast poultry operations) | F8: Poultry, Animal feed (corn, soy) | G8: 4 | H8: 2 | I8: 4 | J8: 3 | K8: 3 | L8: 0 | M8: 3.3 | N8: Tier 2 | P8: [REMOVED] Major US poultry producer (private). Integrated operations - hatcheries, feed mills, processing. Contract grower model. Source: Perdue Farms website.
A9: Suntory | B9: Japan | C9: Asia | D9: Beverage conglomerate | E9: Japan, USA, Europe (limited direct farming) | F9: Barley, Grapes (whisky, wine), Tea | G9: 2 | H9: 4 | I9: 3 | J9: 3 | K9: 4 | L9: -1 | M9: 3.05 | N9: Tier 3 | P9: Japanese beverage giant (Beam Suntory whisky, soft drinks). Some vineyard ownership. Sources barley, botanicals. Source: Suntory Annual Reports.
A10: Meiji Holdings | B10: Japan | C10: Asia | D10: Dairy & confectionery manufacturer | E10: Japan, China, SE Asia | F10: Dairy, Cocoa, Sugar | G10: 2 | H10: 3 | I10: 3 | J10: 3 | K10: 3 | L10: -1 | M10: 2.75 | N10: Tier 3 | P10: Japanese dairy and confectionery company. Meiji Bulgaria yogurt, chocolate. Sources from dairy farmers. Source: Meiji Holdings Annual Reports.
A11: Del Monte Foods | B11: USA | C11: North America | D11: Integrated produce company | E11: USA, Philippines, Kenya, Costa Rica (plantations) | F11: Pineapples, Bananas, Tomatoes, Vegetables | G11: 5 | H11: 4 | I11: 3 | J11: 4 | K11: 4 | L11: -1 | M11: 4.25 | N11: Tier 1 | P11: Vertically integrated "farm to store". Owns pineapple/banana plantations in Philippines, Kenya, Costa Rica. Strong integration model. Source: Del Monte Pacific Annual Reports.
A12: Dole Food Company | B12: USA | C12: North America | D12: Integrated produce company | E12: Honduras, Costa Rica, Ecuador, Philippines (plantations) | F12: Bananas, Pineapples, Berries, Fresh vegetables | G12: 5 | H12: 5 | I12: 3 | J12: 5 | K12: 5 | L12: -1 | M12: 4.7 | N12: Tier 1 | P12: World's largest producer of fruits/vegetables. Owns extensive plantations in Latin America, Philippines. Highly integrated fresh produce. Source: Dole plc Annual Reports.
A13: Chiquita Brands | B13: USA | C13: North America | D13: Integrated banana producer | E13: Guatemala, Honduras, Panama, Costa Rica, Ecuador | F13: Bananas, Pineapples | G13: 5 | H13: 4 | I13: 3 | J13: 4 | K13: 4 | L13: 0 | M13: 4.15 | N13: Tier 1 | P13: Major banana producer (owned by Cutrale-Safra). Owns plantations across Central/South America. Strong vertical integration. Source: Chiquita company information.
A14: Syngenta Group | B14: Switzerland | C14: Europe | D14: Agrochemical & seeds company | E14: Global (R&D farms, demonstration sites) | F14: Seeds, Crop protection (all major crops) | G14: 2 | H14: 3 | I14: 3 | J14: 5 | K14: 5 | L14: -1 | M14: 3.15 | N14: Tier 3 | P14: Major agrochemical company (owned by ChemChina). Could be strategic partner for biostimulant distribution. Strong farmer relationships globally. Source: Syngenta Annual Reports.
A15: Corteva Agriscience | B15: USA | C15: North America | D15: Agrochemical & seeds company | E15: Global (R&D farms, demonstration sites) | F15: Seeds, Crop protection (corn, soy, wheat) | G15: 2 | H15: 2 | I15: 4 | J15: 5 | K15: 5 | L15: -1 | M15: 3.1 | N15: Tier 3 | P15: Major ag company (spun from DowDuPont). Pioneer seeds, crop protection. Potential distribution partner. Source: Corteva Annual Reports.
A16: Ingredion | B16: USA | C16: North America | D16: Ingredient solutions provider | E16: USA, Mexico, Brazil, Thailand, Pakistan | F16: Corn, Tapioca, Potatoes (starches) | G16: 3 | H16: 2 | I16: 4 | J16: 4 | K16: 3 | L16: 0 | M16: 3.1 | N16: Tier 3 | P16: Global ingredient company - starches, sweeteners. Sources corn and tapioca. Some direct farmer programs. Source: Ingredion Annual Reports.
A17: McCormick & Company | B17: USA | C17: North America | D17: Spice & flavor manufacturer | E17: Vietnam, India, Indonesia, Madagascar (spice sourcing) | F17: Pepper, Vanilla, Cinnamon, Herbs, Spices | G17: 3 | H17: 5 | I17: 3 | J17: 4 | K17: 4 | L17: -1 | M17: 3.8 | N17: Tier 2 | P17: World's largest spice company. Direct farmer sourcing programs in origins. High-value specialty crops. Sustainable sourcing commitments. Source: McCormick Annual Reports.
... A55: Calavo Growers | B55: USA | C55: North America | D55: Avocado/fresh food company | E55: USA, Mexico | F55: Avocados, Tomatoes, Guacamole | G55: 3 | H55: 5 | I55: 4 | J55: 3 | K55: 3 | L55: 0 | M55: 3.7 | N55: Tier 2 | P55: Major avocado handler/processor. Works with avocado growers in California, Mexico. Fresh and prepared foods. Source: Calavo Growers Annual Reports.

Sheet Matrix - Top 101-150
A1: Decision Matrix - Target Partners (Top 51-100 food companies globally)
A2: Scores are 0–5. Weighted score and tier update automatically based on Assumptions tab.
A4: Company | B4: HQ Country | C4: Region | D4: Business Type (eg. integrated producer) | E4: Countries with controlled farms | F4: Main crops (top 5) | G4: Integration / Owns Land (0–5) | H4: High-Value Crop Exposure (0–5) | I4: Registration Ease (0–5) | J4: Scale Potential (0–5) | K4: Strategic Leverage (0–5) | L4: Penalty: Complexity (0–-2) | M4: Weighted Score (0–5) | N4: Tier | O4: Owner | P4: Notes / Evidence
A5: Top 101-150 food companies in the world
A6: Bonduelle | B6: France | C6: Europe | D6: Vegetable processor | E6: France, Hungary, Poland, Russia, USA, Canada | F6: Peas, Corn, Beans, Carrots, Spinach | G6: 4 | H6: 3 | I6: 5 | J6: 4 | K6: 3 | L6: 0 | M6: 3.9 | N6: Tier 2 | P6: [REMOVED] European leader in processed vegetables. Works with contract growers across Europe. Strong EU presence with clear biostimulant pathways. Source: Bonduelle Annual Reports.
A7: Citrus World (Florida's Natural) | B7: USA | C7: North America | D7: Citrus cooperative | E7: USA (Florida citrus groves) | F7: Oranges, Grapefruit, Citrus | G7: 5 | H7: 4 | I7: 4 | J7: 3 | K7: 3 | L7: 0 | M7: 4.15 | N7: Tier 1 | P7: Florida citrus cooperative (Florida's Natural brand). Grower-owned. Integrated citrus operations. High-value crop facing greening disease pressure. Source: Florida's Natural company information.
A8: Sunkist Growers | B8: USA | C8: North America | D8: Citrus cooperative | E8: USA (California, Arizona citrus) | F8: Oranges, Lemons, Grapefruit, Mandarins | G8: 4 | H8: 4 | I8: 4 | J8: 4 | K8: 4 | L8: 0 | M8: 4 | N8: Tier 1 | P8: Major US citrus cooperative. ~2,000 grower members. Strong brand, influence over farming practices. Source: Sunkist company information.
A9: Blue Diamond Growers | B9: USA | C9: North America | D9: Almond cooperative | E9: USA (California almonds) | F9: Almonds | G9: 4 | H9: 5 | I9: 4 | J9: 5 | K9: 5 | L9: 0 | M9: 4.45 | N9: Tier 1 | P9: World's largest almond processor. Cooperative of ~3,000 California growers. High-value tree nuts. Strong influence over farming practices. Source: Blue Diamond company information.
A10: Diamond Foods (Snyder's-Lance) | B10: USA | C10: North America | D10: Snack food manufacturer | E10: USA (walnut sourcing) | F10: Walnuts, Snack ingredients | G10: 2 | H10: 4 | I10: 4 | J10: 2 | K10: 2 | L10: 0 | M10: 2.9 | N10: Tier 3 | P10: Walnut processor (now part of Campbell's via Snyder's-Lance). Sources from California walnut growers. Source: Campbell's Annual Reports.
A11: Setton Pistachio | B11: USA | C11: North America | D11: Pistachio processor | E11: USA (California pistachios) | F11: Pistachios | G11: 4 | H11: 5 | I11: 4 | J11: 3 | K11: 3 | L11: 0 | M11: 4.05 | N11: Tier 1 | P11: Major California pistachio processor. Owns orchards and works with growers. High-value tree nuts. Source: Setton Pistachio company information.
A12: Wonderful Company (Paramount Farms) | B12: USA | C12: North America | D12: Integrated nut/citrus producer | E12: USA (California - extensive orchards) | F12: Pistachios, Almonds, Pomegranates, Citrus, Mandarins | G12: 5 | H12: 5 | I12: 4 | J12: 5 | K12: 5 | L12: 0 | M12: 4.8 | N12: Tier 1 | P12: Owns 120,000+ acres of orchards in California. Wonderful Pistachios, POM Wonderful, Halos mandarins. Highly integrated, high-value crops. Excellent target. Source: Wonderful Company information.
A13: Ocean Spray | B13: USA | C13: North America | D13: Cranberry cooperative | E13: USA, Canada, Chile (cranberry bogs) | F13: Cranberries, Blueberries | G13: 4 | H13: 4 | I13: 4 | J13: 4 | K13: 4 | L13: 0 | M13: 4 | N13: Tier 1 | P13: World's largest cranberry cooperative. ~700 grower families. Strong influence over farming practices. High-value berries. Source: Ocean Spray company information.
A14: Welch's | B14: USA | C14: North America | D14: Grape cooperative | E14: USA (Concord grape regions) | F14: Concord grapes, Niagara grapes | G14: 4 | H14: 4 | I14: 4 | J14: 3 | K14: 3 | L14: 0 | M14: 3.8 | N14: Tier 2 | P14: Grape cooperative (National Grape Cooperative). ~900 grower families. Welch's brand. Source: Welch's company information.
A15: TreeTop | B15: USA | C15: North America | D15: Apple cooperative | E15: USA (Washington State apples) | F15: Apples, Pears | G15: 4 | H15: 4 | I15: 4 | J15: 3 | K15: 3 | L15: 0 | M15: 3.8 | N15: Tier 2 | P15: Apple grower cooperative in Washington State. ~1,100 grower members. Apple juice, applesauce. Source: TreeTop company information.
A16: Stemilt Growers | B16: USA | C16: North America | D16: Integrated tree fruit producer | E16: USA (Washington State) | F16: Apples, Cherries, Pears | G16: 5 | H16: 5 | I16: 4 | J16: 4 | K16: 4 | L16: 0 | M16: 4.6 | N16: Tier 1 | P16: Major Washington State tree fruit grower. Owns orchards, packing facilities. Premium fruit varieties. Family-owned. Source: Stemilt company information.
A17: CMI Orchards | B17: USA | C17: North America | D17: Integrated apple producer | E17: USA (Washington State) | F17: Apples (Ambrosia, Kanzi, KIKU) | G17: 5 | H17: 5 | I17: 4 | J17: 4 | K17: 4 | L17: 0 | M17: 4.6 | N17: Tier 1 | P17: Major apple grower/marketer. Owns orchards, manages proprietary varieties. Premium apple focus. Source: CMI Orchards company information.
... A55: Driscoll's of the Americas | B55: USA | C55: North America | D55: Berry genetics/licensing | E55: USA, Mexico, Argentina, Peru, Morocco | F55: Strawberry, Raspberry, Blueberry, Blackberry genetics | G55: 3 | H55: 5 | I55: 4 | J55: 5 | K55: 5 | L55: 0 | M55: 4.1 | N55: Tier 1 | P55: Berry genetics company (related to Driscoll's). Licenses proprietary berry varieties to independent growers globally. Strong influence over berry farming practices through genetic material. Source: Driscoll's company information.

Sheet Matrix - Refined list
A1: Refined List of Companies | C1: Key: | D1: Green = Current Lead, Tier 1
D2: Orange = Current Lead, Tier 2
D3: Yellow = Tier 1/2 target
A4: Company | B4: HQ Country | C4: Region | D4: Business Type (eg. integrated producer) | E4: Countries with controlled farms | F4: Main crops (top 5) | G4: Integration / Owns Land (0–5) | H4: High-Value Crop Exposure (0–5) | I4: Registration Ease (0–5) | J4: Scale Potential (0–5) | K4: Strategic Leverage (0–5) | L4: Penalty: Complexity (0–-2) | M4: Weighted Score (0–5) | N4: Tier | O4: Owner | P4: Notes / Evidence
A5: Associated British Foods | B5: UK | C5: Europe | D5: Diversified food & retail | E5: UK, Spain, China, Australia (sugar, ingredients) | F5: Sugar (beet/cane), Wheat, Yeast ingredients | G5: 4 | H5: 2 | I5: 3 | J5: 4 | K5: 3 | L5: -1 | M5: 3.35 | N5: Tier 2 | P5: [Illovo Sugar only: 75K+ ha Africa]
A6: Olam | B6: Singapore | C6: Asia | D6: Integrated agribusiness | E6: Africa, Asia, Australia, Americas (extensive farm ownership) | F6: Cocoa, Coffee, Nuts, Spices, Cotton, Rice, Rubber | G6: 5 | H6: 4 | I6: 2 | J6: 5 | K6: 4 | L6: -1 | M6: 4.2 | N6: Tier 1 | P6: Major integrated agribusiness. Owns ~700,000+ ha farmland (almond orchards, coffee estates, cocoa farms, palm plantations). Highly integrated from farm to customer. Strong position in specialty crops. Source: Olam Annual Reports.
A7: Del Monte Foods | B7: USA | C7: North America | D7: Integrated produce company | E7: USA, Philippines, Kenya, Costa Rica (plantations) | F7: Pineapples, Bananas, Tomatoes, Vegetables | G7: 5 | H7: 4 | I7: 3 | J7: 4 | K7: 4 | L7: -1 | M7: 4.25 | N7: Tier 1 | O7: Sophia | P7: Vertically integrated "farm to store". Owns pineapple/banana plantations in Philippines, Kenya, Costa Rica. Strong integration model. Source: Del Monte Pacific Annual Reports.
A8: Dole Food Company | B8: USA | C8: North America | D8: Integrated produce company | E8: Honduras, Costa Rica, Ecuador, Philippines (plantations) | F8: Bananas, Pineapples, Berries, Fresh vegetables | G8: 5 | H8: 5 | I8: 3 | J8: 5 | K8: 5 | L8: -1 | M8: 4.7 | N8: Tier 1 | O8: Sophia | P8: World's largest producer of fruits/vegetables. Owns extensive plantations in Latin America, Philippines. Highly integrated fresh produce. Source: Dole plc Annual Reports.
A9: Chiquita Brands | B9: USA | C9: North America | D9: Integrated banana producer | E9: Guatemala, Honduras, Panama, Costa Rica, Ecuador | F9: Bananas, Pineapples | G9: 5 | H9: 4 | I9: 3 | J9: 4 | K9: 4 | L9: 0 | M9: 4.15 | N9: Tier 1 | P9: Major banana producer (owned by Cutrale-Safra). Owns plantations across Central/South America. Strong vertical integration. Source: Chiquita company information.
A10: SLC Agrícola | B10: Brazil | C10: Latin America | D10: Large-scale crop producer | E10: Brazil (extensive farmland) | F10: Soybeans, Cotton, Corn | G10: 5 | H10: 2 | I10: 3 | J10: 5 | K10: 4 | L10: 0 | M10: 3.8 | N10: Tier 2 | P10: One of Brazil's largest farming companies. Owns/operates ~700,000+ ha of farmland. Highly integrated row crop production. Excellent biostimulant target. Source: SLC Agrícola Annual Reports.
A11: Adecoagro | B11: Luxembourg | C11: Other | D11: Integrated agribusiness | E11: Argentina, Brazil, Uruguay (farmland) | F11: Sugar cane, Grains, Dairy, Rice | G11: 5 | H11: 3 | I11: 3 | J11: 4 | K11: 3 | L11: 0 | M11: 3.85 | N11: Tier 2 | P11: Owns ~230,000 ha farmland in South America. Sugar mills, dairy farms, grain operations. Highly integrated agricultural company. Source: Adecoagro Annual Reports.
A12: Cresud | B12: Argentina | C12: Other | D12: Agricultural land company | E12: Argentina, Brazil, Paraguay, Bolivia | F12: Soybeans, Corn, Wheat, Cattle | G12: 5 | H12: 2 | I12: 3 | J12: 4 | K12: 3 | L12: 0 | M12: 3.6 | N12: Tier 2 | P12: Major South American farmland company. Owns ~800,000+ ha. Row crops and cattle operations. Parent of IRSA. Source: Cresud Annual Reports.
A13: Greenyard | B13: Belgium | C13: Other | D13: Fresh produce supplier | E13: Belgium, Netherlands, Spain, Poland, USA | F13: Fresh fruits, Vegetables, Frozen produce | G13: 3 | H13: 4 | I13: 5 | J13: 4 | K13: 3 | L13: 0 | M13: 3.8 | N13: Tier 2 | P13: Major European fresh produce supplier. Works with grower networks. Supplies retailers. Some owned growing operations. EU biostimulant-friendly. Source: Greenyard Annual Reports.
A14: Total Produce (Dole plc) | B14: Ireland | C14: Other | D14: Fresh produce distributor | E14: Europe, USA, South Africa (fresh produce) | F14: Fresh fruits, Vegetables | G14: 3 | H14: 4 | I14: 4 | J14: 4 | K14: 4 | L14: 0 | M14: 3.65 | N14: Tier 2 | P14: Now part of Dole plc. Major fresh produce distributor in Europe/US. Works with grower networks. Source: Dole plc Annual Reports.
A15: Driscoll's | B15: USA | C15: North America | D15: Berry producer/marketer | E15: USA, Mexico, Peru, Spain, Morocco, Australia | F15: Strawberries, Raspberries, Blueberries, Blackberries | G15: 4 | H15: 5 | I15: 4 | J15: 5 | K15: 5 | L15: 0 | M15: 4.45 | N15: Tier 1 | P15: World's largest berry producer (private). Works with independent growers using Driscoll's genetics. High-value crops with quality premiums. Strong farmer relationships. Source: Driscoll's company information.
A16: Sun World International | B16: USA | C16: North America | D16: Table grape/stone fruit producer | E16: USA, Chile, Peru, South Africa, Australia, Spain | F16: Table grapes, Stone fruits (proprietary varieties) | G16: 4 | H16: 5 | I16: 4 | J16: 4 | K16: 4 | L16: 0 | M16: 4.25 | N16: Tier 1 | P16: Premium fruit IP company. Licenses proprietary grape/stone fruit varieties to growers globally. Strong influence over farming practices. Source: Sun World company information.
A17: Zespri International | B17: New Zealand | C17: Oceania | D17: Kiwifruit marketer | E17: New Zealand, Italy, France, Japan, Korea | F17: Kiwifruit (green, gold, red) | G17: 4 | H17: 5 | I17: 5 | J17: 4 | K17: 5 | L17: 0 | M17: 4.5 | N17: Tier 1 | O17: David | P17: World's largest kiwifruit marketer. Works with NZ growers (cooperative model). High-value fruit with premium positioning. Strong sustainability programs. Source: Zespri Annual Reports.
A18: T&G Global (Turners & Growers) | B18: New Zealand | C18: Oceania | D18: Integrated fresh produce | E18: New Zealand, Australia, USA, Europe | F18: Apples (Jazz, Envy), Tomatoes, Berries | G18: 4 | H18: 5 | I18: 5 | J18: 3 | K18: 4 | L18: 0 | M18: 4.3 | N18: Tier 1 | P18: NZ fresh produce company. Owns orchards, proprietary apple varieties (Jazz, Envy). Integrated operations. Source: T&G Global Annual Reports.
A19: Costa Group | B19: Australia | C19: Other | D19: Integrated fresh produce | E19: Australia, Morocco, China | F19: Berries, Tomatoes, Avocados, Citrus, Mushrooms | G19: 5 | H19: 5 | I19: 5 | J19: 4 | K19: 4 | L19: 0 | M19: 4.8 | N19: Tier 1 | P19: Australia's largest fresh produce company. Owns farms across multiple categories. Highly integrated. Australia has excellent biostimulant pathways. Source: Costa Group Annual Reports.
A20: Seeka | B20: New Zealand | C20: Oceania | D20: Integrated kiwifruit/avocado | E20: New Zealand, Australia | F20: Kiwifruit, Avocados | G20: 4 | H20: 5 | I20: 5 | J20: 3 | K20: 3 | L20: 0 | M20: 4.25 | N20: Tier 1 | P20: Major NZ kiwifruit/avocado grower and post-harvest operator. Owns orchards. Strong integration in NZ horticulture. Source: Seeka Annual Reports.
A21: Fyffes | B21: Ireland | C21: Other | D21: Fresh produce importer | E21: Costa Rica, Honduras, Colombia, Ecuador (bananas) | F21: Bananas, Melons, Pineapples | G21: 4 | H21: 4 | I21: 4 | J21: 3 | K21: 3 | L21: 0 | M21: 3.8 | N21: Tier 2 | O21: Sophia | P21: Major European banana importer (owned by Sumitomo). Owns banana farms in Central America. Source: Fyffes/Sumitomo company information.
A22: Fresh Del Monte Produce | B22: USA | C22: North America | D22: Integrated fresh produce | E22: Costa Rica, Guatemala, Kenya, Philippines (plantations) | F22: Bananas, Pineapples, Melons, Vegetables | G22: 5 | H22: 4 | I22: 3 | J22: 4 | K22: 4 | L22: 0 | M22: 4.15 | N22: Tier 1 | P22: Major fresh produce company (separate from Del Monte Foods). Owns plantations. Vertically integrated. Source: Fresh Del Monte Annual Reports.
A23: Mission Produce | B23: USA | C23: North America | D23: Avocado producer/distributor | E23: USA (California), Mexico, Peru, Colombia | F23: Avocados | G23: 4 | H23: 5 | I23: 4 | J23: 4 | K23: 4 | L23: 0 | M23: 4.25 | N23: Tier 1 | P23: World's largest avocado distributor. Owns farms in California, Peru. High-value crop. Strong grower relationships. Source: Mission Produce Annual Reports.
A24: Calavo Growers | B24: USA | C24: North America | D24: Avocado/fresh food company | E24: USA, Mexico | F24: Avocados, Tomatoes, Guacamole | G24: 3 | H24: 5 | I24: 4 | J24: 3 | K24: 3 | L24: 0 | M24: 3.7 | N24: Tier 2 | P24: Major avocado handler/processor. Works with avocado growers in California, Mexico. Fresh and prepared foods. Source: Calavo Growers Annual Reports.
A25: Citrus World (Florida's Natural) | B25: USA | C25: North America | D25: Citrus cooperative | E25: USA (Florida citrus groves) | F25: Oranges, Grapefruit, Citrus | G25: 5 | H25: 4 | I25: 4 | J25: 3 | K25: 3 | L25: 0 | M25: 4.15 | N25: Tier 1 | P25: Florida citrus cooperative (Florida's Natural brand). Grower-owned. Integrated citrus operations. High-value crop facing greening disease pressure. Source: Florida's Natural company information.
A26: Sunkist Growers | B26: USA | C26: North America | D26: Citrus cooperative | E26: USA (California, Arizona citrus) | F26: Oranges, Lemons, Grapefruit, Mandarins | G26: 4 | H26: 4 | I26: 4 | J26: 4 | K26: 4 | L26: 0 | M26: 4 | N26: Tier 1 | P26: Major US citrus cooperative. ~2,000 grower members. Strong brand, influence over farming practices. Source: Sunkist company information.
A27: Blue Diamond Growers | B27: USA | C27: North America | D27: Almond cooperative | E27: USA (California almonds) | F27: Almonds | G27: 4 | H27: 5 | I27: 4 | J27: 5 | K27: 5 | L27: 0 | M27: 4.45 | N27: Tier 1 | P27: World's largest almond processor. Cooperative of ~3,000 California growers. High-value tree nuts. Strong influence over farming practices. Source: Blue Diamond company information.
A28: Setton Pistachio | B28: USA | C28: North America | D28: Pistachio processor | E28: USA (California pistachios) | F28: Pistachios | G28: 4 | H28: 5 | I28: 4 | J28: 3 | K28: 3 | L28: 0 | M28: 4.05 | N28: Tier 1 | P28: Major California pistachio processor. Owns orchards and works with growers. High-value tree nuts. Source: Setton Pistachio company information.
A29: Wonderful Company (Paramount Farms) | B29: USA | C29: North America | D29: Integrated nut/citrus producer | E29: USA (California - extensive orchards) | F29: Pistachios, Almonds, Pomegranates, Citrus, Mandarins | G29: 5 | H29: 5 | I29: 4 | J29: 5 | K29: 5 | L29: 0 | M29: 4.8 | N29: Tier 1 | P29: Owns 120,000+ acres of orchards in California. Wonderful Pistachios, POM Wonderful, Halos mandarins. Highly integrated, high-value crops. Excellent target. Source: Wonderful Company information.
A30: Ocean Spray | B30: USA | C30: North America | D30: Cranberry cooperative | E30: USA, Canada, Chile (cranberry bogs) | F30: Cranberries, Blueberries | G30: 4 | H30: 4 | I30: 4 | J30: 4 | K30: 4 | L30: 0 | M30: 4 | N30: Tier 1 | P30: World's largest cranberry cooperative. ~700 grower families. Strong influence over farming practices. High-value berries. Source: Ocean Spray company information.
A31: Welch's | B31: USA | C31: North America | D31: Grape cooperative | E31: USA (Concord grape regions) | F31: Concord grapes, Niagara grapes | G31: 4 | H31: 4 | I31: 4 | J31: 3 | K31: 3 | L31: 0 | M31: 3.8 | N31: Tier 2 | P31: Grape cooperative (National Grape Cooperative). ~900 grower families. Welch's brand. Source: Welch's company information.
A32: TreeTop | B32: USA | C32: North America | D32: Apple cooperative | E32: USA (Washington State apples) | F32: Apples, Pears | G32: 4 | H32: 4 | I32: 4 | J32: 3 | K32: 3 | L32: 0 | M32: 3.8 | N32: Tier 2 | P32: Apple grower cooperative in Washington State. ~1,100 grower members. Apple juice, applesauce. Source: TreeTop company information.
A33: Stemilt Growers | B33: USA | C33: North America | D33: Integrated tree fruit producer | E33: USA (Washington State) | F33: Apples, Cherries, Pears | G33: 5 | H33: 5 | I33: 4 | J33: 4 | K33: 4 | L33: 0 | M33: 4.6 | N33: Tier 1 | P33: Major Washington State tree fruit grower. Owns orchards, packing facilities. Premium fruit varieties. Family-owned. Source: Stemilt company information.
... A70: Driscoll's of the Americas | B70: USA | C70: North America | D70: Berry genetics/licensing | E70: USA, Mexico, Argentina, Peru, Morocco | F70: Strawberry, Raspberry, Blueberry, Blackberry genetics | G70: 3 | H70: 5 | I70: 4 | J70: 5 | K70: 5 | L70: 0 | M70: 4.1 | N70: Tier 1 | P70: Berry genetics company (related to Driscoll's). Licenses proprietary berry varieties to independent growers globally. Strong influence over berry farming practices through genetic material. Source: Driscoll's company information.

Sheet Scoring Guide
A1: Scoring Guide
A3: Metric | B3: Score | C3: Definition (practical test) | D3: Definition (broader)
A4: Integration (owns/controls land + can mandate practices) | B4: 0 | C4: No land control. Pure brand/manufacturer/retailer. | D4: No owned/controlled production. Pure buyer/brand.
B5: 1 | C5: Mostly independent growers. Limited influence via buying/standards. | D5: Some long-term grower programs but no owned land.
B6: 2 | C6: Some owned/leased estates but small share of volume; limited program standardization.
B7: 3 | C7: Material owned/controlled hectares + central agronomy; can standardize on estates. | D7: Meaningful owned/leased land or tight grower control (multi-year); harvest data accessible.
B8: 4 | C8: Large estate footprint + harvest control + packhouse/processing control + traceability.
B9: 5 | C9: Can roll out a standard program across regions in 1–2 seasons; strong data and governance. | D9: Large owned/leased footprint; consistent agronomy/harvest data; can run multi-site trials fast.
A11: High-value crop exposure. Value-at-stake (crop economics + biostimulant leverage) | B11: 0 | C11: Low €/ha crops with low quality premiums. Hard to justify spend. | D11: Mostly low-value commodities; limited margin leverage.
B12: 1 | C12: Moderate €/ha but thin margins; limited grade/pack-out upside. | D12: Mix of commodities and some higher-value crops.
B13: 2 | C13: Mixed portfolio; some high-value crops but not core.
B14: 3 | C14: Meaningful high-value crops where quality/pack-out drives revenue. | D14: Material exposure to higher-value crops where yield/grade matters (horticulture, specialty).
B15: 4 | C15: Strongly weighted to high-value horticulture (fresh produce, berries, grapes, tree crops, specialty veg).
B16: 5 | C16: Premium-heavy portfolio with tight specs; small quality shifts drive big revenue per hectare. | D16: High concentration in high-value crops with strong quality grade economics (fresh produce, berries, specialty).
A18: RegEase (registration + deployability across footprint) | B18: 0 | C18: Blocked / not feasible for intended use or claims right now. | D18: Multiple hard-to-register markets; long timelines; uncertain pathway.
B19: 1 | C19: High friction: slow/uncertain pathway; expensive; restrictive. | D19: Some hard markets; partner has limited regulatory support.
B20: 2 | C20: Challenging but possible with significant local work and time.
B21: 3 | C21: Moderate: known pathway but still needs dossier + local support. | D21: Operates mainly in markets with clear biostimulant pathways; strong internal regulatory capacity.
B22: 4 | C22: Relatively straightforward in most operating countries.
B23: 5 | C23: Clear pathways + you already have (or can quickly obtain) approvals in core countries. | D23: Operates mainly in markets with clear biostimulant pathways; strong internal regulatory capacity.
A25: Scale Potential | B25: 0 | C25: Small footprint; limited acreage or fragmented operations.
B26: 1 | C26: Medium footprint; scaling would require many sites.
B27: 2
B28: 3 | C28: Large footprint or centralized decision-making across multiple farms/regions.
B29: 4
B30: 5 | C30: Very large footprint; centralized procurement/agronomy; fast replication across regions.
A32: Strategic Leverage | B32: 0 | C32: Low brand/reference value; limited ecosystem influence.
B33: 1 | C33: Some reference value; regional influence.
B34: 2
B35: 3 | C35: Strong category reference; opens doors to peers/traders/retailers.
B36: 4
B37: 5 | C37: Global reference account; creates follow-on demand + strong marketing/validation value.
A39: Penalty: Complexity (0,-1,-2) | B39: 0 | C39: Straightforward procurement + trials
B40: -1 | C40: moderate complexity (multiple BUs, heavy legal);
B41: -2 | C41: very complex or high risk (strong incumbent lock-in, long procurement cycles).
A43: Bonuses & Penalty | B43: 0–3 | C43: Centralized procurement + willingness to sign multi-year, multi-region agreements; predictable acreage.
A44: Bonuses & Penalty | B44: 0–2 | C44: Block-level traceability, packhouse data, disciplined trials; easier to prove ROI.
A45: Bonuses & Penalty | B45: -2..0 | C45: Risk of upsetting distributor channel or pricing conflicts. -2 = high risk.

Sheet Top 50 by Region
A1: Top 50 food companies (publicly traded) by revenue (TTM) – grouped by HQ region
A2: Source: CompaniesMarketCap 'Top publicly traded food companies by revenue' (TTM). Note: this excludes large private companies (e.g., Cargill, Mars).
A3: Source URL | B3: https://companiesmarketcap.com/food/largest-food-companies-by-revenue/
A5: Rank | B5: Company | C5: TTM Revenue (USD B) | D5: HQ Country | E5: Region | F5: Notes
A6: North America
A7: 4 | B7: Archer Daniels Midland (ADM) | C7: 83.21 | D7: USA | E7: North America
A8: 5 | B8: Sysco | C8: 82.03 | D8: USA | E8: North America
A9: 6 | B9: Performance Food Group | C9: 64.95 | D9: USA | E9: North America
A10: 7 | B10: Bunge Global SA | C10: 60.1 | D10: USA | E10: North America
A11: 9 | B11: Tyson Foods | C11: 54.44 | D11: USA | E11: North America
A12: 10 | B12: George Weston | C12: 45.38 | D12: Canada | E12: North America
A13: 13 | B13: US Foods | C13: 39.11 | D13: USA | E13: North America
A14: 14 | B14: Mondelez International | C14: 37.64 | D14: USA | E14: North America
A15: 18 | B15: McDonald | C15: 26.26 | D15: USA | E15: North America
A16: 19 | B16: Kraft Heinz | C16: 25.16 | D16: USA | E16: North America
A17: 21 | B17: Empire Company | C17: 22.54 | D17: Canada | E17: North America
A18: 25 | B18: General Mills | C18: 18.77 | D18: USA | E18: North America
... A30: 48 | B30: Campbell's | C30: 10.15 | D30: USA | E30: North America
A32: Latin America
A33: 3 | B33: JBS N.V. | C33: 86.06 | D33: Brazil | E33: Latin America
A34: 15 | B34: Marfrig Global Foods | C34: 28.71 | D34: Brazil | E34: Latin America
A35: 23 | B35: Grupo Bimbo | C35: 21.54 | D35: Mexico | E35: Latin America
A37: Europe
A38: 1 | B38: Ahold Delhaize | C38: 103.02 | D38: Netherlands | E38: Europe
A39: 2 | B39: Nestlé | C39: 101.54 | D39: Switzerland | E39: Europe
A40: 8 | B40: Unilever | C40: 58.59 | D40: UK | E40: Europe
A41: 12 | B41: Compass Group | C41: 42 | D41: UK | E41: Europe
A42: 17 | B42: Associated British Foods | C42: 26.35 | D42: UK | E42: Europe
A43: 29 | B43: Sodexo | C43: 17.06 | D43: France | E43: Europe
A44: 31 | B44: Danone | C44: 16.43 | D44: France | E44: Europe
A45: 36 | B45: DSM-Firmenich | C45: 13.31 | D45: Switzerland | E45: Europe
A46: 41 | B46: Barry Callebaut | C46: 12.21 | D46: Switzerland | E46: Europe
A47: 49 | B47: Südzucker | C47: 10.07 | D47: Germany | E47: Europe
A49: Africa
A50: 40 | B50: Bid Corp | C50: 12.52 | D50: South Africa | E50: Africa
A52: Asia
A53: 11 | B53: Wilmar International | C53: 42.64 | D53: Singapore | E53: Asia
A54: 16 | B54: WH Group | C54: 27.85 | D54: Hong Kong | E54: Asia
A55: 20 | B55: Olam | C55: 24.27 | D55: Singapore | E55: Asia
A56: 22 | B56: Muyuan Foods | C56: 21.93 | D56: China | E56: Asia
A57: 24 | B57: Uni-President Enterprises | C57: 21.38 | D57: Taiwan | E57: Asia
A58: 28 | B58: Charoen Pokphand Foods | C58: 17.41 | D58: Thailand | E58: Asia
A59: 30 | B59: Guangdong HAID Group | C59: 16.88 | D59: China | E59: Asia
A60: 33 | B60: Kirin Holdings | C60: 15.03 | D60: Japan | E60: Asia
A61: 42 | B61: Mengniu Dairy | C61: 12.15 | D61: China | E61: Asia
A62: 45 | B62: Yum China | C62: 11.56 | D62: China | E62: Asia
A63: 50 | B63: Ajinomoto | C63: 9.82 | D63: Japan | E63: Asia
A65: Oceania
A66: 34 | B66: Fonterra | C66: 13.58 | D66: New Zealand | E66: Oceania

Sheet Assumptions
A1: Assumptions (edit weights + tier thresholds)
A3: Weights (must sum to 1.0 for E–I). Penalty weight should be negative.
A4: Metric | B4: Weight
A5: Integration / Owns Land | B5: 0.35
A6: High-Value Crop Exposure | B6: 0.2
A7: Registration Ease | B7: 0.1
A8: Scale Potential | B8: 0.3
A9: Strategic Leverage | B9: 0.05
A10: Penalty: Complexity | B10: -0.1
A11: Weights sum (E–I) | B11: =SUM(B5:B9) -> 1
A13: Tier thresholds (Weighted Score)
A14: Tier 1 ≥ | B14: 4
A15: Tier 2 ≥ | B15: 3.2
A16: Tier 3 ≥ | B16: 2.5

Sheet Lists
A1: Country | B1: Region
A2: Brazil | B2: Latin America
A3: Canada | B3: North America
A4: China | B4: Asia
A5: France | B5: Europe
A6: Germany | B6: Europe
A7: Hong Kong | B7: Asia
A8: Japan | B8: Asia
A9: Mexico | B9: Latin America
A10: Netherlands | B10: Europe
A11: New Zealand | B11: Oceania
A12: Singapore | B12: Asia
... A18: USA | B18: North America

Sheet Removed Companies
A1: Company | B1: HQ | C1: Region | D1: Type | E1: Crops | F1: Score | G1: Tier | H1: Reason
A2: Hormel Foods | B2: USA | C2: =IFERROR(VLOOKUP(B48,Lists!$A$2:$B$200,2,FALSE()),"North America") -> North America | D2: Food manufacturer/processor | E2: Pork, Turkey, Nuts, Vegetables | F2: =IFERROR((G48*Assumptions!$B$5 + H48*Assumptions!$B$6 + I48*Assumptions!$B$7 + J48*Assumptions!$B$8 + K48*Assumptions!$B$9 + L48*Assumptions!$B$10),"" ) -> 0 | G2: =IF(M48="","",IF(M48>=Assumptions!$B$14,"Tier 1",IF(M48>=Assumptions!$B$15,"Tier 2",IF(M48>=Assumptions!$B$16,"Tier 3","Tier 4")))) | H2: Processor. No direct crop control.
A3: Südzucker | B3: Germany | C3: =IFERROR(VLOOKUP(B54,Lists!$A$2:$B$200,2,FALSE()),"Europe") -> Europe | D3: Sugar & food ingredients producer | E3: Sugar beet, Bioethanol feedstocks | F3: =IFERROR((G54*Assumptions!$B$5 + H54*Assumptions!$B$6 + I54*Assumptions!$B$7 + J54*Assumptions!$B$8 + K54*Assumptions!$B$9 + L54*Assumptions!$B$10),"" ) -> 0 | G3: =IF(M54="","",IF(M54>=Assumptions!$B$14,"Tier 1",IF(M54>=Assumptions!$B$15,"Tier 2",IF(M54>=Assumptions!$B$16,"Tier 3","Tier 4")))) | H3: Processor. Sugar from contracted beet growers.
A4: Ajinomoto | B4: Japan | C4: =IFERROR(VLOOKUP(B55,Lists!$A$2:$B$200,2,FALSE()),"Asia") -> Asia | D4: Food & amino acid manufacturer | E4: Amino acids, MSG, Seasonings (sugar cane, tapioca) | F4: =IFERROR((G55*Assumptions!$B$5 + H55*Assumptions!$B$6 + I55*Assumptions!$B$7 + J55*Assumptions!$B$8 + K55*Assumptions!$B$9 + L55*Assumptions!$B$10),"" ) -> 0 | G4: =IF(M55="","",IF(M55>=Assumptions!$B$14,"Tier 1",IF(M55>=Assumptions!$B$15,"Tier 2",IF(M55>=Assumptions!$B$16,"Tier 3","Tier 4")))) | H4: Ingredient mfr. No centralized farm programs.
A5: Perdue Farms | B5: USA | C5: North America | D5: Integrated poultry processor | E5: Poultry, Animal feed (corn, soy) | F5: 3.3 | G5: Tier 2 | H5: Processor. Poultry, limited crop agronomy.
A6: Lamb Weston | B6: USA | C6: North America | D6: Frozen potato processor | E6: Potatoes (processing varieties) | F6: 3.4 | G6: Tier 2 | H6: Processor. No direct farm control.
A7: McCain Foods | B7: Canada | C7: North America | D7: Frozen potato processor | E7: Potatoes | F7: 3.55 | G7: Tier 2 | H7: Processor. No farm-level input control.
A8: Gruma | B8: Mexico | C8: Latin America | D8: Corn flour & tortilla producer | E8: Corn (white and yellow) | F8: 2.9 | G8: Tier 3 | H8: Processor. Buys corn from market.
A9: San Miguel Corporation | B9: Philippines | C9: Other | D9: Diversified conglomerate | E9: Poultry, Pork, Animal feed | F9: 3.1 | G9: Tier 3 | H9: Conglomerate (PH). Poultry/pork focus.
A10: Indofood Sukses Makmur | B10: Indonesia | C10: Other | D10: Diversified food conglomerate | E10: Palm oil, Wheat (noodles), Sugar | F10: 3.15 | G10: Tier 3 | H10: Conglomerate. Agriculture not core.
A11: Bonduelle | B11: France | C11: Europe | D11: Vegetable processor | E11: Peas, Corn, Beans, Carrots, Spinach | F11: 3.9 | G11: Tier 2 | H11: Processor. Sources from independent growers.
A13: PRINCIPLE: | B13: Removed: no farm-level agronomic control at scale.

Sheet Watch List
A1: Company | B1: HQ | C1: Region | D1: Type | E1: Crops | F1: Score | G1: Tier | H1: Why Watch | I1: Re-entry Trigger
A2: Barry Callebaut | B2: Switzerland | C2: =IFERROR(VLOOKUP(B46,Lists!$A$2:$B$200,2,FALSE()),"Europe") -> Europe | D2: Cocoa & chocolate manufacturer | E2: Cocoa, Chocolate | F2: =IFERROR((G46*Assumptions!$B$5 + H46*Assumptions!$B$6 + I46*Assumptions!$B$7 + J46*Assumptions!$B$8 + K46*Assumptions!$B$9 + L46*Assumptions!$B$10),"" ) -> 0 | G2: =IF(M46="","",IF(M46>=Assumptions!$B$14,"Tier 1",IF(M46>=Assumptions!$B$15,"Tier 2",IF(M46>=Assumptions!$B$16,"Tier 3","Tier 4")))) | H2: 200K+ farmer cocoa programs. No direct hectare control. | I2: If BC launches centralized input program or cocoa biostimulant trials.
A3: Ferrero | B3: Italy | C3: Other | D3: Confectionery manufacturer | E3: Hazelnuts, Cocoa, Palm oil, Sugar | F3: 4.25 | G3: Tier 1 | H3: Own hazelnut farming (Agri Alba Chile, Turkey). Not yet at scale. | I3: When hazelnut ops reach 10K+ ha direct control.
